{"brcId":null,"docId":"doc-86-598.txt","annotations":[[{"startNode":{"id":3683,"offset":1839},"endNode":{"id":3684,"offset":1859},"id":3840,"type":"Mention","features":{"Experiencer":"Patient","Negation":"Negated","PREF":"History","STY":"Finding","TUI":"T033","tui_full":"http://linkedlifedata.com/resource/semanticnetwork/id/T033","Temporality":"historical","VOCABS":"NCI","inst":"C0262926","language":"","string_orig":"past medical history","inst_full":"http://linkedlifedata.com/resource/umls/id/C0262926"}},{"startNode":{"id":3685,"offset":1878},"endNode":{"id":3686,"offset":1885},"id":3841,"type":"Mention","features":{"language":"","Experiencer":"Patient","Negation":"Negated","PREF":"Medical","tui_full":"http://linkedlifedata.com/resource/semanticnetwork/id/T058","STY":"Health Care Activity","TUI":"T058","Temporality":"historical","VOCABS":"HL7V3.0","inst":"C0199168","string_orig":"medical","inst_full":"http://linkedlifedata.com/resource/umls/id/C0199168"}},{"startNode":{"id":3687,"offset":1896},"endNode":{"id":3688,"offset":1900},"id":3842,"type":"Mention","features":{"Negation":"Affirmed","Experiencer":"Patient","PREF":"In the past","STY":"Temporal Concept","TUI":"T079","Temporality":"Recent","VOCABS":"LNC,NCI,SNOMEDCT_US","inst":"C1444637","language":"","string_orig":"past","tui_full":"http://linkedlifedata.com/resource/semanticnetwork/id/T079","inst_full":"http://linkedlifedata.com/resource/umls/id/C1444637"}},{"startNode":{"id":3596,"offset":393},"endNode":{"id":3597,"offset":397},"id":3843,"type":"Mention","features":{"Experiencer":"Patient","Negation":"Affirmed","PREF":"Painful","STY":"Sign or Symptom","TUI":"T184","Temporality":"Recent","VOCABS":"CSP,CHV,AOD,BI,ICPC2ICD10ENG,ICPC2P,MEDCIN,PDQ","inst":"C0030193","language":"","string_orig":"pain","inst_full":"http://linkedlifedata.com/resource/umls/id/C0030193","tui_full":"http://linkedlifedata.com/resource/semanticnetwork/id/T184"}},{"startNode":{"id":3689,"offset":1901},"endNode":{"id":3690,"offset":1917},"id":3844,"type":"Mention","features":{"PREF":"HISTORY SURGICAL","Experiencer":"Patient","Negation":"Affirmed","STY":"Finding","TUI":"T033","Temporality":"historical","VOCABS":"CCPSS,CHV,MEDCIN","inst":"C0744961","language":"","string_orig":"surgical history","tui_full":"http://linkedlifedata.com/resource/semanticnetwork/id/T033","inst_full":"http://linkedlifedata.com/resource/umls/id/C0744961"}},{"startNode":{"id":3829,"offset":3584},"endNode":{"id":3830,"offset":3589},"id":3845,"type":"Mention","features":{"Experiencer":"Patient","Negation":"Negated","PREF":"Dropsy","STY":"Pathologic Function","TUI":"T046","Temporality":"Recent","VOCABS":"RCDSA,OMIM,LNC,NCI_NCI-GLOSS,HPO,BI,MTH,CHV,SNM,NDFRT,SNOMEDCT_US,AOD,RCDAE,LCH_NW,NCI_NICHD,ICPC2ICD10ENG,MDR,UWDA,CSP,MSH,NOC,LCH,RCD,NANDA-I,OMS,NCI,NCI_FDA,ICD9CM,MEDLINEPLUS,MEDCIN","inst":"C0013604","language":"","string_orig":"edema","inst_full":"http://linkedlifedata.com/resource/umls/id/C0013604","tui_full":"http://linkedlifedata.com/resource/semanticnetwork/id/T046"}},{"startNode":{"id":3691,"offset":1921},"endNode":{"id":3692,"offset":1928},"id":3846,"type":"Mention","features":{"Negation":"Affirmed","Experiencer":"Patient","PREF":"Surgery","STY":"Therapeutic or Preventive Procedure","tui_full":"http://linkedlifedata.com/resource/semanticnetwork/id/T061","TUI":"T061","Temporality":"historical","VOCABS":"CSP,CHV,MEDCIN,PDQ,NCI_NCI-GLOSS","inst":"C0543467","language":"","string_orig":"surgery","inst_full":"http://linkedlifedata.com/resource/umls/id/C0543467"}},{"startNode":{"id":3693,"offset":1933},"endNode":{"id":3694,"offset":1941},"id":3847,"type":"Mention","features":{"Negation":"Affirmed","Experiencer":"Patient","PREF":"Removal","tui_full":"http://linkedlifedata.com/resource/semanticnetwork/id/T061","STY":"Therapeutic or Preventive Procedure","TUI":"T061","Temporality":"historical","VOCABS":"CHV","inst":"C0015252","language":"","string_orig":"excision","inst_full":"http://linkedlifedata.com/resource/umls/id/C0015252"}},{"startNode":{"id":3831,"offset":3591},"endNode":{"id":3832,"offset":3595},"id":3848,"type":"Mention","features":{"PREF":"Skin NOS","Experiencer":"Patient","Negation":"Affirmed","STY":"Body System","TUI":"T022","Temporality":"Recent","VOCABS":"CSP,CHV,AOD","inst":"C1123023","language":"","string_orig":"skin","inst_full":"http://linkedlifedata.com/resource/umls/id/C1123023","tui_full":"http://linkedlifedata.com/resource/semanticnetwork/id/T022"}},{"startNode":{"id":3695,"offset":1966},"endNode":{"id":3696,"offset":1970},"id":3849,"type":"Mention","features":{"language":"","Experiencer":"Patient","Negation":"Affirmed","PREF":"Shot","STY":"Therapeutic or Preventive Procedure","TUI":"T061","Temporality":"historical","VOCABS":"CHV","tui_full":"http://linkedlifedata.com/resource/semanticnetwork/id/T061","inst":"C0021485","string_orig":"shot","inst_full":"http://linkedlifedata.com/resource/umls/id/C0021485"}},{"startNode":{"id":3833,"offset":3598},"endNode":{"id":3834,"offset":3602},"id":3850,"type":"Mention","features":{"TUI":"T033","Experiencer":"Patient","Negation":"Affirmed","PREF":"Feels warm","STY":"Finding","Temporality":"Recent","VOCABS":"LNC","inst":"C0582051","language":"","string_orig":"warm","tui_full":"http://linkedlifedata.com/resource/semanticnetwork/id/T033","inst_full":"http://linkedlifedata.com/resource/umls/id/C0582051"}},{"startNode":{"id":3598,"offset":416},"endNode":{"id":3599,"offset":421},"id":3851,"type":"Mention","features":{"Experiencer":"Patient","Negation":"Affirmed","PREF":"Itching","STY":"Finding","TUI":"T033","Temporality":"Recent","VOCABS":"CHV,RCD,SNOMEDCT_US,MDR","inst":"C0033774","tui_full":"http://linkedlifedata.com/resource/semanticnetwork/id/T033","language":"","string_orig":"itchy","inst_full":"http://linkedlifedata.com/resource/umls/id/C0033774"}},{"startNode":{"id":3697,"offset":1991},"endNode":{"id":3698,"offset":1997},"id":3852,"type":"Mention","features":{"Experiencer":"Patient","Negation":"Affirmed","PREF":"Habits","STY":"Individual Behavior","TUI":"T055","Temporality":"Recent","VOCABS":"CHV,MSH,RCD,SNOMEDCT_US,PSY","inst":"C0018464","language":"","string_orig":"habits","inst_full":"http://linkedlifedata.com/resource/umls/id/C0018464","tui_full":"http://linkedlifedata.com/resource/semanticnetwork/id/T055"}},{"startNode":{"id":3835,"offset":3604},"endNode":{"id":3836,"offset":3607},"id":3853,"type":"Mention","features":{"Negation":"Affirmed","Experiencer":"Patient","PREF":"Dry Skin","STY":"Sign or Symptom","TUI":"T184","Temporality":"Recent","VOCABS":"LNC,OMIM","inst":"C0151908","tui_full":"http://linkedlifedata.com/resource/semanticnetwork/id/T184","language":"","string_orig":"dry","inst_full":"http://linkedlifedata.com/resource/umls/id/C0151908"}},{"startNode":{"id":3699,"offset":2028},"endNode":{"id":3700,"offset":2038},"id":3854,"type":"Mention","features":{"VOCABS":"MTH,CHV,PSY,AOD","Experiencer":"Patient","Negation":"Negated","PREF":"Drug use","STY":"Mental or Behavioral Dysfunction","TUI":"T048","Temporality":"Recent","inst":"C0242510","language":"","string_orig":"drug usage","inst_full":"http://linkedlifedata.com/resource/umls/id/C0242510","tui_full":"http://linkedlifedata.com/resource/semanticnetwork/id/T048"}},{"startNode":{"id":3837,"offset":3613},"endNode":{"id":3838,"offset":3619},"id":3855,"type":"Mention","features":{"PREF":"Intact","Experiencer":"Patient","Negation":"Affirmed","STY":"Finding","TUI":"T033","Temporality":"Recent","tui_full":"http://linkedlifedata.com/resource/semanticnetwork/id/T033","VOCABS":"HL7V3.0","inst":"C1554187","language":"","string_orig":"intact","inst_full":"http://linkedlifedata.com/resource/umls/id/C1554187"}},{"startNode":{"id":3701,"offset":2044},"endNode":{"id":3702,"offset":2056},"id":3856,"type":"Mention","features":{"VOCABS":"LNC,NCI","Experiencer":"Patient","Negation":"Affirmed","PREF":"Sometimes","tui_full":"http://linkedlifedata.com/resource/semanticnetwork/id/T079","STY":"Temporal Concept","TUI":"T079","Temporality":"Recent","inst":"C1998882","language":"","string_orig":"occasionally","inst_full":"http://linkedlifedata.com/resource/umls/id/C1998882"}},{"startNode":{"id":3600,"offset":454},"endNode":{"id":3559,"offset":469},"id":3857,"type":"Mention","features":{"STY":"Finding","Experiencer":"Patient","Negation":"Affirmed","PREF":"Sexually active","TUI":"T033","Temporality":"Recent","VOCABS":"CHV,MEDCIN,MDR,RCD,SNOMEDCT_US,DXP","inst":"C0241028","language":"","string_orig":"sexually active","tui_full":"http://linkedlifedata.com/resource/semanticnetwork/id/T033","inst_full":"http://linkedlifedata.com/resource/umls/id/C0241028"}},{"startNode":{"id":3703,"offset":2057},"endNode":{"id":3704,"offset":2063},"id":3858,"type":"Mention","features":{"PREF":"Smoking","Experiencer":"Patient","Negation":"Affirmed","STY":"Individual Behavior","TUI":"T055","Temporality":"Recent","VOCABS":"CHV","inst":"C0037369","language":"","tui_full":"http://linkedlifedata.com/resource/semanticnetwork/id/T055","string_orig":"smokes","inst_full":"http://linkedlifedata.com/resource/umls/id/C0037369"}},{"startNode":{"id":3705,"offset":2076},"endNode":{"id":3706,"offset":2090},"id":3859,"type":"Mention","features":{"Experiencer":"Patient","Negation":"Affirmed","PREF":"Alcohol user","STY":"Individual Behavior","TUI":"T055","Temporality":"Recent","VOCABS":"RCD,SNOMEDCT_US","inst":"C0556297","language":"","tui_full":"http://linkedlifedata.com/resource/semanticnetwork/id/T055","string_orig":"drinks alcohol","inst_full":"http://linkedlifedata.com/resource/umls/id/C0556297"}},{"startNode":{"id":3839,"offset":3625},"endNode":{"id":3840,"offset":3629},"id":3860,"type":"Mention","features":{"PREF":"Rashes","Experiencer":"Patient","tui_full":"http://linkedlifedata.com/resource/semanticnetwork/id/T184","Negation":"Negated","STY":"Sign or Symptom","TUI":"T184","Temporality":"Recent","VOCABS":"LNC,MSH,OMIM,NOC,HPO,BI,CHV,SNM,RCD,SNOMEDCT_US,NDFRT,AOD,NANDA-I,NCI_FDA,NCI_NICHD,ICPC2ICD10ENG,MDR,MEDCIN,OMS","inst":"C0015230","language":"","string_orig":"rash","inst_full":"http://linkedlifedata.com/resource/umls/id/C0015230"}},{"startNode":{"id":3707,"offset":2092},"endNode":{"id":3708,"offset":2104},"id":3861,"type":"Mention","features":{"Temporality":"Recent","Experiencer":"Patient","Negation":"Affirmed","PREF":"medications:","tui_full":"http://linkedlifedata.com/resource/semanticnetwork/id/T058","STY":"Health Care Activity","TUI":"T058","VOCABS":"MEDCIN","inst":"C2094204","language":"","string_orig":"medications:","inst_full":"http://linkedlifedata.com/resource/umls/id/C2094204"}},{"startNode":{"id":3588,"offset":3633},"endNode":{"id":3589,"offset":3639},"id":3862,"type":"Mention","features":{"TUI":"T033","Experiencer":"Patient","Negation":"Negated","PREF":"Lesion","STY":"Finding","Temporality":"Recent","VOCABS":"MTH,SNM,RCD,NCI,SNOMEDCT_US,AOD,CHV,NCI_NCI-GLOSS","inst":"C0221198","language":"","string_orig":"lesion","inst_full":"http://linkedlifedata.com/resource/umls/id/C0221198","tui_full":"http://linkedlifedata.com/resource/semanticnetwork/id/T033"}},{"startNode":{"id":3709,"offset":2113},"endNode":{"id":3710,"offset":2122},"id":3863,"type":"Mention","features":{"Negation":"Affirmed","Experiencer":"Patient","PREF":"Allergy","STY":"Pathologic Function","TUI":"T046","Temporality":"Recent","tui_full":"http://linkedlifedata.com/resource/semanticnetwork/id/T046","VOCABS":"LNC,MSH,OMIM,CHV","inst":"C0020517","language":"","string_orig":"allergies","inst_full":"http://linkedlifedata.com/resource/umls/id/C0020517"}},{"startNode":{"id":3601,"offset":484},"endNode":{"id":3602,"offset":494},"id":3864,"type":"Mention","features":{"VOCABS":"CHV,RCD,NCI,SNOMEDCT_US","Experiencer":"Patient","Negation":"Affirmed","PREF":"Monogamous","STY":"Finding","TUI":"T033","Temporality":"Recent","inst":"C0558125","language":"","string_orig":"monogamous","inst_full":"http://linkedlifedata.com/resource/umls/id/C0558125","tui_full":"http://linkedlifedata.com/resource/semanticnetwork/id/T033"}},{"startNode":{"id":3711,"offset":2135},"endNode":{"id":3712,"offset":2142},"id":3865,"type":"Mention","features":{"inst":"C0199168","Experiencer":"Patient","Negation":"Negated","PREF":"Medical","STY":"Health Care Activity","TUI":"T058","Temporality":"Recent","tui_full":"http://linkedlifedata.com/resource/semanticnetwork/id/T058","VOCABS":"HL7V3.0","language":"","string_orig":"medical","inst_full":"http://linkedlifedata.com/resource/umls/id/C0199168"}},{"startNode":{"id":3841,"offset":3641},"endNode":{"id":3842,"offset":3659},"id":3866,"type":"Mention","features":{"VOCABS":"AIR","PREF":"DIAG TESTS","Experiencer":"Patient","Negation":"Affirmed","STY":"Diagnostic Procedure","TUI":"T060","Temporality":"Recent","inst":"C0086143","language":"","tui_full":"http://linkedlifedata.com/resource/semanticnetwork/id/T060","string_orig":"diagnostic studies","inst_full":"http://linkedlifedata.com/resource/umls/id/C0086143"}},{"startNode":{"id":3713,"offset":2143},"endNode":{"id":3714,"offset":2152},"id":3867,"type":"Mention","features":{"STY":"Pathologic Function","Experiencer":"Patient","Negation":"Negated","PREF":"Allergy","TUI":"T046","Temporality":"Recent","VOCABS":"LNC,MSH,OMIM,CHV","inst":"C0020517","language":"","string_orig":"allergies","inst_full":"http://linkedlifedata.com/resource/umls/id/C0020517","tui_full":"http://linkedlifedata.com/resource/semanticnetwork/id/T046"}},{"startNode":{"id":3715,"offset":2154},"endNode":{"id":3716,"offset":2174},"id":3868,"type":"Mention","features":{"Temporality":"Recent","PREF":"Physical","Experiencer":"Patient","Negation":"Affirmed","STY":"Health Care Activity","TUI":"T058","tui_full":"http://linkedlifedata.com/resource/semanticnetwork/id/T058","VOCABS":"MTH,MSH,CCC,LNC,AOT,CPT,ALT,AIR,NCI_NCI-GLOSS,NCI_CDISC,CHV,SNM,RCD,NCI,SNOMEDCT_US,PSY,AOD,NCI_NICHD,NCI_CTRP,MDR,ICNP,MEDCIN","inst":"C0031809","language":"","string_orig":"physical examination","inst_full":"http://linkedlifedata.com/resource/umls/id/C0031809"}},{"startNode":{"id":3843,"offset":3667},"endNode":{"id":3844,"offset":3687},"id":3869,"type":"Mention","features":{"TUI":"T093","Experiencer":"Patient","Negation":"Affirmed","PREF":"Emergency","STY":"Health Care Related Organization","Temporality":"Recent","VOCABS":"CHV","inst":"C0562508","language":"","string_orig":"emergency department","tui_full":"http://linkedlifedata.com/resource/semanticnetwork/id/T093","inst_full":"http://linkedlifedata.com/resource/umls/id/C0562508"}},{"startNode":{"id":3717,"offset":2178},"endNode":{"id":3718,"offset":2185},"id":3870,"type":"Mention","features":{"Negation":"Affirmed","Experiencer":"Patient","PREF":"General","STY":"Health Care Activity","TUI":"T058","Temporality":"Recent","VOCABS":"HL7V3.0","inst":"C3812897","language":"","tui_full":"http://linkedlifedata.com/resource/semanticnetwork/id/T058","string_orig":"general","inst_full":"http://linkedlifedata.com/resource/umls/id/C3812897"}},{"startNode":{"id":3845,"offset":3688},"endNode":{"id":3846,"offset":3695},"id":3871,"type":"Mention","features":{"Negation":"Affirmed","Experiencer":"Patient","PREF":"Course","STY":"Temporal Concept","tui_full":"http://linkedlifedata.com/resource/semanticnetwork/id/T079","TUI":"T079","Temporality":"Recent","VOCABS":"CHV,RCD,SNOMEDCT_US","inst":"C0750729","language":"","string_orig":"courses","inst_full":"http://linkedlifedata.com/resource/umls/id/C0750729"}},{"startNode":{"id":3719,"offset":2244},"endNode":{"id":3720,"offset":2247},"id":3872,"type":"Mention","features":{"STY":"Clinical Attribute","Experiencer":"Patient","Negation":"Affirmed","PREF":"Age","TUI":"T201","Temporality":"Recent","VOCABS":"LNC","tui_full":"http://linkedlifedata.com/resource/semanticnetwork/id/T201","inst":"C1114365","language":"","string_orig":"age","inst_full":"http://linkedlifedata.com/resource/umls/id/C1114365"}},{"startNode":{"id":3847,"offset":3704},"endNode":{"id":3848,"offset":3711},"id":3873,"type":"Mention","features":{"PREF":"Thought","Experiencer":"Patient","Negation":"Affirmed","STY":"Mental Process","TUI":"T041","Temporality":"Recent","VOCABS":"NCI","inst":"C0039869","language":"","string_orig":"thought","tui_full":"http://linkedlifedata.com/resource/semanticnetwork/id/T041","inst_full":"http://linkedlifedata.com/resource/umls/id/C0039869"}},{"startNode":{"id":3721,"offset":2254},"endNode":{"id":3722,"offset":2259},"id":3874,"type":"Mention","features":{"Experiencer":"Patient","Negation":"Affirmed","PREF":"Year","STY":"Temporal Concept","TUI":"T079","Temporality":"Recent","VOCABS":"CHV,RCD,SNOMEDCT_US","inst":"C0439234","language":"","string_orig":"years","tui_full":"http://linkedlifedata.com/resource/semanticnetwork/id/T079","inst_full":"http://linkedlifedata.com/resource/umls/id/C0439234"}},{"startNode":{"id":3849,"offset":3761},"endNode":{"id":3850,"offset":3772},"id":3875,"type":"Mention","features":{"PREF":"Referral to","Experiencer":"Patient","Negation":"Affirmed","STY":"Health Care Activity","TUI":"T058","Temporality":"Recent","VOCABS":"MEDCIN,SNOMEDCT_US","tui_full":"http://linkedlifedata.com/resource/semanticnetwork/id/T058","inst":"C2585021","language":"","string_orig":"referral to","inst_full":"http://linkedlifedata.com/resource/umls/id/C2585021"}},{"startNode":{"id":3723,"offset":2268},"endNode":{"id":3724,"offset":2282},"id":3876,"type":"Mention","features":{"Negation":"Affirmed","Experiencer":"Patient","PREF":"Well nourished","STY":"Finding","TUI":"T033","Temporality":"Recent","VOCABS":"RCD,SNOMEDCT_US","inst":"C2364291","language":"","string_orig":"well nourished","inst_full":"http://linkedlifedata.com/resource/umls/id/C2364291","tui_full":"http://linkedlifedata.com/resource/semanticnetwork/id/T033"}},{"startNode":{"id":3603,"offset":594},"endNode":{"id":3604,"offset":604},"id":3877,"type":"Mention","features":{"Temporality":"Recent","Experiencer":"Patient","Negation":"Affirmed","PREF":"Monogamous","STY":"Finding","TUI":"T033","VOCABS":"CHV,RCD,NCI,SNOMEDCT_US","inst":"C0558125","language":"","string_orig":"monogamous","inst_full":"http://linkedlifedata.com/resource/umls/id/C0558125","tui_full":"http://linkedlifedata.com/resource/semanticnetwork/id/T033"}},{"startNode":{"id":3725,"offset":2300},"endNode":{"id":3726,"offset":2320},"id":3878,"type":"Mention","features":{"Experiencer":"Patient","Negation":"Negated","PREF":"NAD","STY":"Finding","TUI":"T033","Temporality":"Recent","VOCABS":"MEDCIN","inst":"C2051415","language":"","string_orig":"in no acute distress","tui_full":"http://linkedlifedata.com/resource/semanticnetwork/id/T033","inst_full":"http://linkedlifedata.com/resource/umls/id/C2051415"}},{"startNode":{"id":3851,"offset":3785},"endNode":{"id":3852,"offset":3793},"id":3879,"type":"Mention","features":{"PREF":"Removal","Experiencer":"Patient","Negation":"Affirmed","STY":"Therapeutic or Preventive Procedure","TUI":"T061","Temporality":"Recent","tui_full":"http://linkedlifedata.com/resource/semanticnetwork/id/T061","VOCABS":"CHV","inst":"C0015252","language":"","string_orig":"excision","inst_full":"http://linkedlifedata.com/resource/umls/id/C0015252"}},{"startNode":{"id":3727,"offset":2338},"endNode":{"id":3728,"offset":2346},"id":3880,"type":"Mention","features":{"STY":"Mental Process","Experiencer":"Patient","Negation":"Affirmed","PREF":"Pleasant","TUI":"T041","Temporality":"Recent","VOCABS":"NCI","inst":"C2987187","language":"","tui_full":"http://linkedlifedata.com/resource/semanticnetwork/id/T041","string_orig":"pleasant","inst_full":"http://linkedlifedata.com/resource/umls/id/C2987187"}},{"startNode":{"id":3729,"offset":2355},"endNode":{"id":3730,"offset":2362},"id":3881,"type":"Mention","features":{"Negation":"Affirmed","Experiencer":"Patient","PREF":"Seated","STY":"Finding","TUI":"T033","Temporality":"Recent","VOCABS":"LNC,SNOMEDCT_US,HL7V3.0,NCI,NCI_CDISC,SNMI","inst":"C0277814","tui_full":"http://linkedlifedata.com/resource/semanticnetwork/id/T033","language":"","string_orig":"sitting","inst_full":"http://linkedlifedata.com/resource/umls/id/C0277814"}},{"startNode":{"id":3853,"offset":3798},"endNode":{"id":3854,"offset":3804},"id":3882,"type":"Mention","features":{"Experiencer":"Patient","Negation":"Affirmed","PREF":"Biopsy","STY":"Diagnostic Procedure","TUI":"T060","Temporality":"Recent","VOCABS":"AOD,LNC,MSH,CSP,MTH,CHV,NCI_NCI-GLOSS,MTHMST,LCH,SNM,RCD,NCI,SNOMEDCT_US,PSY,LCH_NW,HL7V2.5,NCI_CTRP,MEDLINEPLUS,MDR,PDQ,MEDCIN","tui_full":"http://linkedlifedata.com/resource/semanticnetwork/id/T060","inst":"C0005558","language":"","string_orig":"biopsy","inst_full":"http://linkedlifedata.com/resource/umls/id/C0005558"}},{"startNode":{"id":3731,"offset":2368},"endNode":{"id":3732,"offset":2388},"id":3883,"type":"Mention","features":{"Negation":"Affirmed","Experiencer":"Patient","PREF":"Emergency","tui_full":"http://linkedlifedata.com/resource/semanticnetwork/id/T093","STY":"Health Care Related Organization","TUI":"T093","Temporality":"Recent","VOCABS":"CHV","inst":"C0562508","language":"","string_orig":"emergency department","inst_full":"http://linkedlifedata.com/resource/umls/id/C0562508"}},{"startNode":{"id":3590,"offset":3813},"endNode":{"id":3591,"offset":3817},"id":3884,"type":"Mention","features":{"PREF":"mass","Experiencer":"Patient","Negation":"Affirmed","STY":"Finding","TUI":"T033","Temporality":"Recent","VOCABS":"MEDCIN","inst":"C2136992","tui_full":"http://linkedlifedata.com/resource/semanticnetwork/id/T033","language":"","string_orig":"mass","inst_full":"http://linkedlifedata.com/resource/umls/id/C2136992"}},{"startNode":{"id":3733,"offset":2397},"endNode":{"id":3734,"offset":2408},"id":3885,"type":"Mention","features":{"VOCABS":"SNM,CCC","Experiencer":"Patient","Negation":"Affirmed","PREF":"Vital Signs","STY":"Health Care Activity","TUI":"T058","Temporality":"Recent","inst":"C0150404","language":"","tui_full":"http://linkedlifedata.com/resource/semanticnetwork/id/T058","string_orig":"vital signs","inst_full":"http://linkedlifedata.com/resource/umls/id/C0150404"}},{"startNode":{"id":3605,"offset":638},"endNode":{"id":3606,"offset":646},"id":3886,"type":"Mention","features":{"PREF":"Practice","Experiencer":"Patient","Negation":"Affirmed","STY":"Mental Process","TUI":"T041","Temporality":"Recent","VOCABS":"CHV","tui_full":"http://linkedlifedata.com/resource/semanticnetwork/id/T041","inst":"C0237607","language":"","string_orig":"practice","inst_full":"http://linkedlifedata.com/resource/umls/id/C0237607"}},{"startNode":{"id":3735,"offset":2411},"endNode":{"id":3736,"offset":2422},"id":3887,"type":"Mention","features":{"VOCABS":"CCC","Experiencer":"Patient","Negation":"Affirmed","PREF":"Temperature","STY":"Health Care Activity","TUI":"T058","Temporality":"Recent","inst":"C0886414","language":"","string_orig":"temperature","tui_full":"http://linkedlifedata.com/resource/semanticnetwork/id/T058","inst_full":"http://linkedlifedata.com/resource/umls/id/C0886414"}},{"startNode":{"id":3756,"offset":2602},"endNode":{"id":3757,"offset":2608},"id":3888,"type":"Mention","features":{"Experiencer":"Patient","Negation":"Negated","PREF":"Murmur","STY":"Finding","TUI":"T033","Temporality":"Recent","VOCABS":"CHV,SNM,ICPC2ICD10ENG,SNOMEDCT_US","inst":"C0018808","language":"","tui_full":"http://linkedlifedata.com/resource/semanticnetwork/id/T033","string_orig":"murmur","inst_full":"http://linkedlifedata.com/resource/umls/id/C0018808"}},{"startNode":{"id":3758,"offset":2641},"endNode":{"id":3759,"offset":2646},"id":3889,"type":"Mention","features":{"Experiencer":"Patient","Negation":"Affirmed","PREF":"Pulmones","tui_full":"http://linkedlifedata.com/resource/semanticnetwork/id/T023","STY":"Body Part, Organ, or Organ Component","TUI":"T023","Temporality":"Recent","VOCABS":"LCH,MSH,NCI,LCH_NW,ICF-CY,FMA,CHV,ICF,UWDA","inst":"C0024109","language":"","string_orig":"lungs","inst_full":"http://linkedlifedata.com/resource/umls/id/C0024109"}},{"startNode":{"id":3574,"offset":2448},"endNode":{"id":3737,"offset":2462},"id":3890,"type":"Mention","features":{"Experiencer":"Patient","Negation":"Affirmed","PREF":"taking of BP","STY":"Health Care Activity","TUI":"T058","Temporality":"Recent","VOCABS":"CHV,MEDCIN","inst":"C0005824","language":"","tui_full":"http://linkedlifedata.com/resource/semanticnetwork/id/T058","string_orig":"blood pressure","inst_full":"http://linkedlifedata.com/resource/umls/id/C0005824"}},{"startNode":{"id":3760,"offset":2649},"endNode":{"id":3761,"offset":2654},"id":3891,"type":"Mention","features":{"Negation":"Affirmed","Experiencer":"Patient","PREF":"Clear Margin","STY":"Finding","TUI":"T033","tui_full":"http://linkedlifedata.com/resource/semanticnetwork/id/T033","Temporality":"Recent","VOCABS":"NCI","inst":"C1709157","language":"","string_orig":"clear","inst_full":"http://linkedlifedata.com/resource/umls/id/C1709157"}},{"startNode":{"id":3762,"offset":2658},"endNode":{"id":3763,"offset":2670},"id":3892,"type":"Mention","features":{"Temporality":"Recent","Experiencer":"Patient","tui_full":"http://linkedlifedata.com/resource/semanticnetwork/id/T060","Negation":"Affirmed","PREF":"Listening","STY":"Diagnostic Procedure","TUI":"T060","VOCABS":"CHV,LCH,MSH,RCD,MTH,SNM,AOD,NCI,LCH_NW,SNOMEDCT_US,LNC,MDR","inst":"C0004339","language":"","string_orig":"auscultation","inst_full":"http://linkedlifedata.com/resource/umls/id/C0004339"}},{"startNode":{"id":3738,"offset":2474},"endNode":{"id":3739,"offset":2479},"id":3893,"type":"Mention","features":{"PREF":"Pulses","Experiencer":"Patient","Negation":"Affirmed","STY":"Health Care Activity","TUI":"T058","tui_full":"http://linkedlifedata.com/resource/semanticnetwork/id/T058","Temporality":"Recent","VOCABS":"MTH,LCH,MSH,CCC,CHV,LCH_NW","inst":"C0034107","language":"","string_orig":"pulse","inst_full":"http://linkedlifedata.com/resource/umls/id/C0034107"}},{"startNode":{"id":3764,"offset":2688},"endNode":{"id":3765,"offset":2695},"id":3894,"type":"Mention","features":{"Experiencer":"Patient","Negation":"Negated","PREF":"Wheeze","STY":"Sign or Symptom","tui_full":"http://linkedlifedata.com/resource/semanticnetwork/id/T184","TUI":"T184","Temporality":"Recent","VOCABS":"CHV,LNC,MDR","inst":"C0043144","language":"","string_orig":"wheezes","inst_full":"http://linkedlifedata.com/resource/umls/id/C0043144"}},{"startNode":{"id":3740,"offset":2487},"endNode":{"id":3741,"offset":2503},"id":3895,"type":"Mention","features":{"STY":"Clinical Attribute","Experiencer":"Patient","Negation":"Affirmed","PREF":"Breath rate","TUI":"T201","Temporality":"Recent","VOCABS":"MTH,NOC,SNM,RCD,SNOMEDCT_US,CHV,MSH,NCI_NICHD,NCI,MDR,NCI_NCPDP,NCI_CDISC","tui_full":"http://linkedlifedata.com/resource/semanticnetwork/id/T201","inst":"C0231832","language":"","string_orig":"respiratory rate","inst_full":"http://linkedlifedata.com/resource/umls/id/C0231832"}},{"startNode":{"id":3766,"offset":2697},"endNode":{"id":3767,"offset":2702},"id":3896,"type":"Mention","features":{"Negation":"Negated","Experiencer":"Patient","PREF":"Crackle","STY":"Finding","tui_full":"http://linkedlifedata.com/resource/semanticnetwork/id/T033","TUI":"T033","Temporality":"Recent","VOCABS":"MTH,MSH,NOC,HPO,ICPC2P,MTHICD9,CHV,SNM,ICD10CM,RCD,SNOMEDCT_US,NCI,RCDSY,ICPC2ICD10ENG,MDR","inst":"C0034642","language":"","string_orig":"rales","inst_full":"http://linkedlifedata.com/resource/umls/id/C0034642"}},{"startNode":{"id":3742,"offset":2515},"endNode":{"id":3743,"offset":2529},"id":3897,"type":"Mention","features":{"TUI":"T060","Experiencer":"Patient","Negation":"Affirmed","PREF":"Pulse Oximetry","STY":"Diagnostic Procedure","Temporality":"Recent","VOCABS":"LNC,CHV,RCD,SNOMEDCT_US,NCI,MSH,NCI_NICHD,MDR,MEDCIN,NCI_CDISC","inst":"C0034108","language":"","string_orig":"pulse oximetry","inst_full":"http://linkedlifedata.com/resource/umls/id/C0034108","tui_full":"http://linkedlifedata.com/resource/semanticnetwork/id/T060"}},{"startNode":{"id":3768,"offset":2707},"endNode":{"id":3769,"offset":2714},"id":3898,"type":"Mention","features":{"string_orig":"rhonchi","Experiencer":"Patient","Negation":"Negated","PREF":"Rhonchi","STY":"Finding","TUI":"T033","Temporality":"Recent","VOCABS":"CHV,MTH,SNM,RCD,SNOMEDCT_US,NCI,HPO,OMIM,NCI_NICHD,MDR,MSH,MEDCIN","inst":"C0035508","tui_full":"http://linkedlifedata.com/resource/semanticnetwork/id/T033","language":"","inst_full":"http://linkedlifedata.com/resource/umls/id/C0035508"}},{"startNode":{"id":3744,"offset":2537},"endNode":{"id":3745,"offset":2548},"id":3899,"type":"Mention","features":{"PREF":"on room air","Experiencer":"Patient","Negation":"Affirmed","STY":"Finding","TUI":"T033","Temporality":"Recent","VOCABS":"LNC","tui_full":"http://linkedlifedata.com/resource/semanticnetwork/id/T033","inst":"C2709070","language":"","string_orig":"on room air","inst_full":"http://linkedlifedata.com/resource/umls/id/C2709070"}},{"startNode":{"id":3748,"offset":2575},"endNode":{"id":3749,"offset":2581},"id":3900,"type":"Mention","features":{"VOCABS":"MTH,CHV,PSY","Experiencer":"Patient","Negation":"Affirmed","PREF":"Rhythm","STY":"Finding","TUI":"T033","Temporality":"Recent","tui_full":"http://linkedlifedata.com/resource/semanticnetwork/id/T033","inst":"C0871269","language":"","string_orig":"rhythm","inst_full":"http://linkedlifedata.com/resource/umls/id/C0871269"}},{"startNode":{"id":3855,"offset":3819},"endNode":{"id":3856,"offset":3829},"id":3901,"type":"Mention","features":{"PREF":"Assessment","Experiencer":"Patient","tui_full":"http://linkedlifedata.com/resource/semanticnetwork/id/T060","Negation":"Affirmed","STY":"Diagnostic Procedure","TUI":"T060","Temporality":"Recent","VOCABS":"PCDS","inst":"C0028708","language":"","string_orig":"assessment","inst_full":"http://linkedlifedata.com/resource/umls/id/C0028708"}},{"startNode":{"id":3750,"offset":2584},"endNode":{"id":3751,"offset":2589},"id":3902,"type":"Mention","features":{"Negation":"Affirmed","Experiencer":"Patient","tui_full":"http://linkedlifedata.com/resource/semanticnetwork/id/T033","PREF":"Clear Margin","STY":"Finding","TUI":"T033","Temporality":"Recent","VOCABS":"NCI","inst":"C1709157","language":"","string_orig":"clear","inst_full":"http://linkedlifedata.com/resource/umls/id/C1709157"}},{"startNode":{"id":3770,"offset":2716},"endNode":{"id":3771,"offset":2723},"id":3903,"type":"Mention","features":{"PREF":"Abdomen","Experiencer":"Patient","Negation":"Affirmed","STY":"Body Location or Region","TUI":"T029","Temporality":"Recent","VOCABS":"CSP,LNC,MSH,CST,MTH,LCH,SNM,RCD,SNOMEDCT_US,PSY,LCH_NW,HL7V2.5,FMA,CHV,AOD,UWDA","inst":"C0000726","language":"","string_orig":"abdomen","tui_full":"http://linkedlifedata.com/resource/semanticnetwork/id/T029","inst_full":"http://linkedlifedata.com/resource/umls/id/C0000726"}},{"startNode":{"id":3607,"offset":661},"endNode":{"id":3608,"offset":665},"id":3904,"type":"Mention","features":{"STY":"Finding","Experiencer":"Patient","Negation":"Affirmed","PREF":"Does","TUI":"T033","Temporality":"Recent","VOCABS":"SNOMEDCT_US","tui_full":"http://linkedlifedata.com/resource/semanticnetwork/id/T033","inst":"C1272751","language":"","string_orig":"does","inst_full":"http://linkedlifedata.com/resource/umls/id/C1272751"}},{"startNode":{"id":3772,"offset":2761},"endNode":{"id":3773,"offset":2769},"id":3905,"type":"Mention","features":{"Temporality":"Recent","Experiencer":"Patient","Negation":"Affirmed","PREF":"Positive","tui_full":"http://linkedlifedata.com/resource/semanticnetwork/id/T033","STY":"Finding","TUI":"T033","VOCABS":"CHV,MTH,HL7V3.0,RCD,SNOMEDCT_US,NCI,SNMI","inst":"C1446409","language":"","string_orig":"positive","inst_full":"http://linkedlifedata.com/resource/umls/id/C1446409"}},{"startNode":{"id":3859,"offset":3842},"endNode":{"id":3593,"offset":3853},"id":3906,"type":"Mention","features":{"inst":"C0240691","Experiencer":"Patient","Negation":"Affirmed","PREF":"Penile Mass","STY":"Finding","TUI":"T033","Temporality":"Recent","VOCABS":"CHV,DXP,MEDCIN,COSTAR,SNOMEDCT_VET","tui_full":"http://linkedlifedata.com/resource/semanticnetwork/id/T033","language":"","string_orig":"penile mass","inst_full":"http://linkedlifedata.com/resource/umls/id/C0240691"}},{"startNode":{"id":3774,"offset":2770},"endNode":{"id":3775,"offset":2782},"id":3907,"type":"Mention","features":{"Experiencer":"Patient","Negation":"Affirmed","PREF":"Borborygmi","STY":"Finding","TUI":"T033","Temporality":"Recent","VOCABS":"CHV,LNC,SNM,RCD,SNOMEDCT_US,MTH,NOC,MEDCIN","inst":"C0232693","language":"","string_orig":"bowel sounds","tui_full":"http://linkedlifedata.com/resource/semanticnetwork/id/T033","inst_full":"http://linkedlifedata.com/resource/umls/id/C0232693"}},{"startNode":{"id":3609,"offset":682},"endNode":{"id":3610,"offset":687},"id":3908,"type":"Mention","features":{"language":"","Experiencer":"Patient","Negation":"Affirmed","PREF":"At night","STY":"Temporal Concept","TUI":"T079","Temporality":"Recent","tui_full":"http://linkedlifedata.com/resource/semanticnetwork/id/T079","VOCABS":"LNC,CHV,NCI,AOD","inst":"C0240526","string_orig":"night","inst_full":"http://linkedlifedata.com/resource/umls/id/C0240526"}},{"startNode":{"id":3752,"offset":2590},"endNode":{"id":3753,"offset":2592},"id":3909,"type":"Mention","features":{"VOCABS":"FMA,UWDA","Experiencer":"Patient","Negation":"Affirmed","PREF":"S1 innervation","STY":"Body Location or Region","TUI":"T029","Temporality":"Recent","inst":"C1179704","language":"","tui_full":"http://linkedlifedata.com/resource/semanticnetwork/id/T029","string_orig":"s1","inst_full":"http://linkedlifedata.com/resource/umls/id/C1179704"}},{"startNode":{"id":3860,"offset":3868},"endNode":{"id":3861,"offset":3872},"id":3910,"type":"Mention","features":{"TUI":"T033","Experiencer":"Patient","Negation":"Affirmed","tui_full":"http://linkedlifedata.com/resource/semanticnetwork/id/T033","PREF":"Does","STY":"Finding","Temporality":"Recent","VOCABS":"SNOMEDCT_US","inst":"C1272751","language":"","string_orig":"does","inst_full":"http://linkedlifedata.com/resource/umls/id/C1272751"}},{"startNode":{"id":3776,"offset":2795},"endNode":{"id":3777,"offset":2808},"id":3911,"type":"Mention","features":{"Temporality":"Recent","Experiencer":"Patient","Negation":"Affirmed","PREF":"Urogenital","STY":"Body System","TUI":"T022","VOCABS":"BI,CHV,SNMI","inst":"C0042066","language":"","tui_full":"http://linkedlifedata.com/resource/semanticnetwork/id/T022","string_orig":"genitourinary","inst_full":"http://linkedlifedata.com/resource/umls/id/C0042066"}},{"startNode":{"id":3611,"offset":737},"endNode":{"id":3612,"offset":745},"id":3912,"type":"Mention","features":{"string_orig":"engaging","Experiencer":"Patient","Negation":"Affirmed","PREF":"Engaged","STY":"Finding","tui_full":"http://linkedlifedata.com/resource/semanticnetwork/id/T033","TUI":"T033","Temporality":"Recent","VOCABS":"CHV","inst":"C0425152","language":"","inst_full":"http://linkedlifedata.com/resource/umls/id/C0425152"}},{"startNode":{"id":3754,"offset":2594},"endNode":{"id":3755,"offset":2596},"id":3913,"type":"Mention","features":{"Experiencer":"Patient","Negation":"Affirmed","PREF":"S2 innervation","STY":"Body Location or Region","TUI":"T029","Temporality":"Recent","tui_full":"http://linkedlifedata.com/resource/semanticnetwork/id/T029","VOCABS":"FMA,UWDA","inst":"C1179705","language":"","string_orig":"s2","inst_full":"http://linkedlifedata.com/resource/umls/id/C1179705"}},{"startNode":{"id":3862,"offset":3899},"endNode":{"id":3595,"offset":3910},"id":3914,"type":"Mention","features":{"Negation":"Affirmed","Experiencer":"Patient","tui_full":"http://linkedlifedata.com/resource/semanticnetwork/id/T033","PREF":"Penile Mass","STY":"Finding","TUI":"T033","Temporality":"Recent","VOCABS":"CHV,DXP,MEDCIN,COSTAR,SNOMEDCT_VET","inst":"C0240691","language":"","string_orig":"penile mass","inst_full":"http://linkedlifedata.com/resource/umls/id/C0240691"}},{"startNode":{"id":3778,"offset":2825},"endNode":{"id":3779,"offset":2843},"id":3915,"type":"Mention","features":{"PREF":"Vulval","Experiencer":"Patient","tui_full":"http://linkedlifedata.com/resource/semanticnetwork/id/T023","Negation":"Affirmed","STY":"Body Part, Organ, or Organ Component","TUI":"T023","Temporality":"Recent","VOCABS":"NCI","inst":"C0042993","language":"","string_orig":"external genitalia","inst_full":"http://linkedlifedata.com/resource/umls/id/C0042993"}},{"startNode":{"id":3613,"offset":749},"endNode":{"id":3614,"offset":767},"id":3916,"type":"Mention","features":{"Experiencer":"Patient","Negation":"Affirmed","PREF":"Coitus","STY":"Finding","TUI":"T033","Temporality":"Recent","VOCABS":"RCD,SNOMEDCT_US,NANDA-I","inst":"C1314687","language":"","string_orig":"sexual intercourse","inst_full":"http://linkedlifedata.com/resource/umls/id/C1314687","tui_full":"http://linkedlifedata.com/resource/semanticnetwork/id/T033"}},{"startNode":{"id":3780,"offset":2856},"endNode":{"id":3781,"offset":2864},"id":3917,"type":"Mention","features":{"STY":"Finding","Experiencer":"Patient","Negation":"Affirmed","PREF":"Abnormal","TUI":"T033","Temporality":"Recent","VOCABS":"CHV,LNC,RCD,MTH,SNOMEDCT_US,NCI_NCI-GLOSS,NCI,SNMI","inst":"C0205161","language":"","string_orig":"abnormal","inst_full":"http://linkedlifedata.com/resource/umls/id/C0205161","tui_full":"http://linkedlifedata.com/resource/semanticnetwork/id/T033"}},{"startNode":{"id":3615,"offset":778},"endNode":{"id":3616,"offset":782},"id":3918,"type":"Mention","features":{"STY":"Temporal Concept","Experiencer":"Patient","Negation":"Affirmed","tui_full":"http://linkedlifedata.com/resource/semanticnetwork/id/T079","PREF":"Time","TUI":"T079","Temporality":"Recent","VOCABS":"CHV","inst":"C0040223","language":"","string_orig":"time","inst_full":"http://linkedlifedata.com/resource/umls/id/C0040223"}},{"startNode":{"id":3576,"offset":2897},"endNode":{"id":3577,"offset":2901},"id":3919,"type":"Mention","features":{"Negation":"Affirmed","Experiencer":"Patient","PREF":"mass","STY":"Finding","TUI":"T033","Temporality":"Recent","VOCABS":"MEDCIN","inst":"C2136992","tui_full":"http://linkedlifedata.com/resource/semanticnetwork/id/T033","language":"","string_orig":"mass","inst_full":"http://linkedlifedata.com/resource/umls/id/C2136992"}},{"startNode":{"id":3782,"offset":2920},"endNode":{"id":3783,"offset":2925},"id":3920,"type":"Mention","features":{"STY":"Body Part, Organ, or Organ Component","Experiencer":"Patient","tui_full":"http://linkedlifedata.com/resource/semanticnetwork/id/T023","Negation":"Affirmed","PREF":"Glans","TUI":"T023","Temporality":"Recent","VOCABS":"HL7V2.5","inst":"C1550261","language":"","string_orig":"glans","inst_full":"http://linkedlifedata.com/resource/umls/id/C1550261"}},{"startNode":{"id":3617,"offset":836},"endNode":{"id":3618,"offset":840},"id":3921,"type":"Mention","features":{"Negation":"Affirmed","Experiencer":"Patient","PREF":"Skin NOS","tui_full":"http://linkedlifedata.com/resource/semanticnetwork/id/T022","STY":"Body System","TUI":"T022","Temporality":"Recent","VOCABS":"CSP,CHV,AOD","inst":"C1123023","language":"","string_orig":"skin","inst_full":"http://linkedlifedata.com/resource/umls/id/C1123023"}},{"startNode":{"id":3784,"offset":2933},"endNode":{"id":3785,"offset":2938},"id":3922,"type":"Mention","features":{"Negation":"Affirmed","Experiencer":"Patient","PREF":"Penile","STY":"Body Part, Organ, or Organ Component","TUI":"T023","Temporality":"Recent","VOCABS":"CSP,MTH,LNC,MSH,NCI_NCI-GLOSS,CHV,LCH,RCD,SNOMEDCT_US,SNM,AOD,LCH_NW,PSY,FMA,HL7V2.5,NCI,UWDA","inst":"C0030851","language":"","string_orig":"penis","inst_full":"http://linkedlifedata.com/resource/umls/id/C0030851","tui_full":"http://linkedlifedata.com/resource/semanticnetwork/id/T023"}},{"startNode":{"id":3786,"offset":2960},"endNode":{"id":3787,"offset":2975},"id":3923,"type":"Mention","features":{"VOCABS":"UWDA,CHV,SNM,FMA,SNOMEDCT_US,SNMI","Experiencer":"Patient","Negation":"Affirmed","PREF":"Urethral meatus","STY":"Body Space or Junction","TUI":"T030","Temporality":"Recent","inst":"C0227744","language":"","string_orig":"urethral meatus","tui_full":"http://linkedlifedata.com/resource/semanticnetwork/id/T030","inst_full":"http://linkedlifedata.com/resource/umls/id/C0227744"}},{"startNode":{"id":3619,"offset":859},"endNode":{"id":3620,"offset":864},"id":3924,"type":"Mention","features":{"STY":"Body Part, Organ, or Organ Component","Experiencer":"Patient","Negation":"Affirmed","PREF":"Penile","TUI":"T023","Temporality":"Recent","VOCABS":"CSP,MTH,LNC,MSH,NCI_NCI-GLOSS,CHV,LCH,RCD,SNOMEDCT_US,SNM,AOD,LCH_NW,PSY,FMA,HL7V2.5,NCI,UWDA","inst":"C0030851","tui_full":"http://linkedlifedata.com/resource/semanticnetwork/id/T023","language":"","string_orig":"penis","inst_full":"http://linkedlifedata.com/resource/umls/id/C0030851"}},{"startNode":{"id":3621,"offset":879},"endNode":{"id":3622,"offset":883},"id":3925,"type":"Mention","features":{"TUI":"T047","Experiencer":"Patient","Negation":"Affirmed","PREF":"Simian AIDS","STY":"Disease or Syndrome","Temporality":"Recent","VOCABS":"CHV","inst":"C0080151","tui_full":"http://linkedlifedata.com/resource/semanticnetwork/id/T047","language":"","string_orig":"said","inst_full":"http://linkedlifedata.com/resource/umls/id/C0080151"}},{"startNode":{"id":3578,"offset":2996},"endNode":{"id":3579,"offset":3000},"id":3926,"type":"Mention","features":{"VOCABS":"MEDCIN","Experiencer":"Patient","Negation":"Affirmed","PREF":"mass","tui_full":"http://linkedlifedata.com/resource/semanticnetwork/id/T033","STY":"Finding","TUI":"T033","Temporality":"Recent","inst":"C2136992","language":"","string_orig":"mass","inst_full":"http://linkedlifedata.com/resource/umls/id/C2136992"}},{"startNode":{"id":3788,"offset":3059},"endNode":{"id":3789,"offset":3064},"id":3927,"type":"Mention","features":{"VOCABS":"CHV","Experiencer":"Patient","tui_full":"http://linkedlifedata.com/resource/semanticnetwork/id/T048","Negation":"Affirmed","PREF":"Stalking","STY":"Mental or Behavioral Dysfunction","TUI":"T048","Temporality":"Recent","inst":"C0935572","language":"","string_orig":"stalk","inst_full":"http://linkedlifedata.com/resource/umls/id/C0935572"}},{"startNode":{"id":3552,"offset":4000},"endNode":{"id":3553,"offset":4004},"id":3928,"type":"Mention","features":{"Experiencer":"Patient","Negation":"Affirmed","PREF":"mass","tui_full":"http://linkedlifedata.com/resource/semanticnetwork/id/T033","STY":"Finding","TUI":"T033","Temporality":"Recent","VOCABS":"MEDCIN","inst":"C2136992","language":"","string_orig":"mass","inst_full":"http://linkedlifedata.com/resource/umls/id/C2136992"}},{"startNode":{"id":3863,"offset":4017},"endNode":{"id":3864,"offset":4025},"id":3929,"type":"Mention","features":{"Experiencer":"Patient","Negation":"Affirmed","PREF":"Biopsy","tui_full":"http://linkedlifedata.com/resource/semanticnetwork/id/T060","STY":"Diagnostic Procedure","TUI":"T060","Temporality":"Recent","VOCABS":"CHV","inst":"C0005558","language":"","string_orig":"biopsied","inst_full":"http://linkedlifedata.com/resource/umls/id/C0005558"}},{"startNode":{"id":3746,"offset":2550},"endNode":{"id":3747,"offset":2555},"id":3930,"type":"Mention","features":{"STY":"Body Part, Organ, or Organ Component","Experiencer":"Patient","Negation":"Affirmed","PREF":"Hearts","TUI":"T023","Temporality":"Recent","VOCABS":"CCPSS,NCI_CDISC,SNMI","tui_full":"http://linkedlifedata.com/resource/semanticnetwork/id/T023","inst":"C0018787","language":"","string_orig":"HEART","inst_full":"http://linkedlifedata.com/resource/umls/id/C0018787"}},{"startNode":{"id":3865,"offset":4051},"endNode":{"id":3866,"offset":4064},"id":3931,"type":"Mention","features":{"inst":"C0162340","Experiencer":"Patient","Negation":"Affirmed","PREF":"Understand","STY":"Mental Process","TUI":"T041","Temporality":"Recent","tui_full":"http://linkedlifedata.com/resource/semanticnetwork/id/T041","VOCABS":"CSP,CHV,SNM,MSH,NCI,SNOMEDCT_US,PSY,AOD","language":"","string_orig":"understanding","inst_full":"http://linkedlifedata.com/resource/umls/id/C0162340"}},{"startNode":{"id":3790,"offset":3087},"endNode":{"id":3791,"offset":3091},"id":3932,"type":"Mention","features":{"Negation":"Affirmed","Experiencer":"Patient","PREF":"2 mm","tui_full":"http://linkedlifedata.com/resource/semanticnetwork/id/T033","STY":"Finding","TUI":"T033","Temporality":"Recent","VOCABS":"LNC","inst":"C3842089","language":"","string_orig":"2 mm","inst_full":"http://linkedlifedata.com/resource/umls/id/C3842089"}},{"startNode":{"id":3560,"offset":916},"endNode":{"id":3561,"offset":921},"id":3933,"type":"Mention","features":{"VOCABS":"MDR","Experiencer":"Patient","Negation":"Affirmed","PREF":"Blood","STY":"Disease or Syndrome","TUI":"T047","Temporality":"Recent","inst":"C0851353","language":"","string_orig":"blood","inst_full":"http://linkedlifedata.com/resource/umls/id/C0851353","tui_full":"http://linkedlifedata.com/resource/semanticnetwork/id/T047"}},{"startNode":{"id":3792,"offset":3166},"endNode":{"id":3793,"offset":3171},"id":3934,"type":"Mention","features":{"VOCABS":"HL7V2.5","Experiencer":"Patient","Negation":"Affirmed","PREF":"Glans","STY":"Body Part, Organ, or Organ Component","TUI":"T023","Temporality":"Recent","inst":"C1550261","language":"","string_orig":"glans","inst_full":"http://linkedlifedata.com/resource/umls/id/C1550261","tui_full":"http://linkedlifedata.com/resource/semanticnetwork/id/T023"}},{"startNode":{"id":3867,"offset":4077},"endNode":{"id":3868,"offset":4085},"id":3935,"type":"Mention","features":{"Negation":"Affirmed","Experiencer":"Patient","PREF":"Followup","STY":"Health Care Activity","TUI":"T058","Temporality":"Recent","VOCABS":"NCI","inst":"C1522577","language":"","tui_full":"http://linkedlifedata.com/resource/semanticnetwork/id/T058","string_orig":"followup","inst_full":"http://linkedlifedata.com/resource/umls/id/C1522577"}},{"startNode":{"id":3623,"offset":932},"endNode":{"id":3624,"offset":938},"id":3936,"type":"Mention","features":{"Experiencer":"Patient","Negation":"Affirmed","PREF":"Injury","STY":"Injury or Poisoning","TUI":"T037","Temporality":"Recent","VOCABS":"CSP,CHV,ICPC2ICD10ENG,ICPC2P,AOD","tui_full":"http://linkedlifedata.com/resource/semanticnetwork/id/T037","inst":"C3263723","language":"","string_orig":"injury","inst_full":"http://linkedlifedata.com/resource/umls/id/C3263723"}},{"startNode":{"id":3794,"offset":3179},"endNode":{"id":3795,"offset":3184},"id":3937,"type":"Mention","features":{"inst":"C0030851","Experiencer":"Patient","Negation":"Affirmed","PREF":"Penile","STY":"Body Part, Organ, or Organ Component","TUI":"T023","Temporality":"Recent","tui_full":"http://linkedlifedata.com/resource/semanticnetwork/id/T023","VOCABS":"CSP,MTH,LNC,MSH,NCI_NCI-GLOSS,CHV,LCH,RCD,SNOMEDCT_US,SNM,AOD,LCH_NW,PSY,FMA,HL7V2.5,NCI,UWDA","language":"","string_orig":"penis","inst_full":"http://linkedlifedata.com/resource/umls/id/C0030851"}},{"startNode":{"id":3625,"offset":960},"endNode":{"id":3626,"offset":965},"id":3938,"type":"Mention","features":{"PREF":"At night","Experiencer":"Patient","Negation":"Affirmed","STY":"Temporal Concept","TUI":"T079","Temporality":"Recent","VOCABS":"LNC,CHV,NCI,AOD","tui_full":"http://linkedlifedata.com/resource/semanticnetwork/id/T079","inst":"C0240526","language":"","string_orig":"night","inst_full":"http://linkedlifedata.com/resource/umls/id/C0240526"}},{"startNode":{"id":3869,"offset":4093},"endNode":{"id":3870,"offset":4103},"id":3939,"type":"Mention","features":{"Negation":"Affirmed","Experiencer":"Patient","PREF":"Release","STY":"Health Care Activity","TUI":"T058","Temporality":"Recent","VOCABS":"LNC,NCI","tui_full":"http://linkedlifedata.com/resource/semanticnetwork/id/T058","inst":"C0030685","language":"","string_orig":"discharged","inst_full":"http://linkedlifedata.com/resource/umls/id/C0030685"}},{"startNode":{"id":3871,"offset":4120},"endNode":{"id":3872,"offset":4129},"id":3940,"type":"Mention","features":{"PREF":"Disease","Experiencer":"Patient","Negation":"Affirmed","STY":"Disease or Syndrome","TUI":"T047","Temporality":"Recent","VOCABS":"NCI_NCI-GLOSS","inst":"C0012634","language":"","string_orig":"condition","tui_full":"http://linkedlifedata.com/resource/semanticnetwork/id/T047","inst_full":"http://linkedlifedata.com/resource/umls/id/C0012634"}},{"startNode":{"id":3796,"offset":3209},"endNode":{"id":3797,"offset":3214},"id":3941,"type":"Mention","features":{"Negation":"Affirmed","Experiencer":"Patient","PREF":"Penile","STY":"Body Part, Organ, or Organ Component","TUI":"T023","Temporality":"Recent","tui_full":"http://linkedlifedata.com/resource/semanticnetwork/id/T023","VOCABS":"CSP,MTH,LNC,MSH,NCI_NCI-GLOSS,CHV,LCH,RCD,SNOMEDCT_US,SNM,AOD,LCH_NW,PSY,FMA,HL7V2.5,NCI,UWDA","inst":"C0030851","language":"","string_orig":"penis","inst_full":"http://linkedlifedata.com/resource/umls/id/C0030851"}},{"startNode":{"id":3627,"offset":1005},"endNode":{"id":3628,"offset":1025},"id":3942,"type":"Mention","features":{"PREF":"Emergency","Experiencer":"Patient","Negation":"Affirmed","STY":"Health Care Related Organization","TUI":"T093","Temporality":"Recent","VOCABS":"CHV","inst":"C0562508","tui_full":"http://linkedlifedata.com/resource/semanticnetwork/id/T093","language":"","string_orig":"emergency department","inst_full":"http://linkedlifedata.com/resource/umls/id/C0562508"}},{"startNode":{"id":3857,"offset":3834},"endNode":{"id":3858,"offset":3838},"id":3943,"type":"Mention","features":{"PREF":"Planning","Experiencer":"Patient","Negation":"Affirmed","STY":"Mental Process","TUI":"T041","Temporality":"Recent","tui_full":"http://linkedlifedata.com/resource/semanticnetwork/id/T041","VOCABS":"CCPSS","inst":"C0032074","language":"","string_orig":"PLAN","inst_full":"http://linkedlifedata.com/resource/umls/id/C0032074"}},{"startNode":{"id":3562,"offset":1048},"endNode":{"id":3563,"offset":1056},"id":3944,"type":"Mention","features":{"STY":"Pathologic Function","Experiencer":"Patient","Negation":"Affirmed","PREF":"Bleeding","tui_full":"http://linkedlifedata.com/resource/semanticnetwork/id/T046","TUI":"T046","Temporality":"Recent","VOCABS":"CSP,LNC,OMIM,NOC,MSH,ICPC2P,CHV,NDFRT,SNM,RCD,NCI,SNOMEDCT_US,NCI_FDA,NCI_NICHD,MEDLINEPLUS,MDR,MEDCIN,ICPC2ICD10ENG,NANDA-I","inst":"C0019080","language":"","string_orig":"bleeding","inst_full":"http://linkedlifedata.com/resource/umls/id/C0019080"}},{"startNode":{"id":3873,"offset":4139},"endNode":{"id":3874,"offset":4141},"id":3945,"type":"Mention","features":{"VOCABS":"NCI_FDA","Experiencer":"Patient","Negation":"Affirmed","PREF":"Adverse Event Emergency Room Visit","STY":"Individual Behavior","TUI":"T055","Temporality":"Recent","inst":"C3810541","language":"","tui_full":"http://linkedlifedata.com/resource/semanticnetwork/id/T055","string_orig":"ER","inst_full":"http://linkedlifedata.com/resource/umls/id/C3810541"}},{"startNode":{"id":3629,"offset":1080},"endNode":{"id":3630,"offset":1084},"id":3946,"type":"Mention","features":{"inst":"C1299581","Experiencer":"Patient","Negation":"Affirmed","PREF":"Able","tui_full":"http://linkedlifedata.com/resource/semanticnetwork/id/T033","STY":"Finding","TUI":"T033","Temporality":"Recent","VOCABS":"CHV,SNOMEDCT_US","language":"","string_orig":"able","inst_full":"http://linkedlifedata.com/resource/umls/id/C1299581"}},{"startNode":{"id":3798,"offset":3243},"endNode":{"id":3799,"offset":3250},"id":3947,"type":"Mention","features":{"TUI":"T033","Experiencer":"Patient","Negation":"Negated","PREF":"Lesion","STY":"Finding","Temporality":"Recent","VOCABS":"CHV,PSY","inst":"C0221198","tui_full":"http://linkedlifedata.com/resource/semanticnetwork/id/T033","language":"","string_orig":"lesions","inst_full":"http://linkedlifedata.com/resource/umls/id/C0221198"}},{"startNode":{"id":3564,"offset":1096},"endNode":{"id":3565,"offset":1104},"id":3948,"type":"Mention","features":{"Negation":"Affirmed","Experiencer":"Patient","PREF":"Bleeding","STY":"Pathologic Function","TUI":"T046","Temporality":"Recent","VOCABS":"CSP,LNC,OMIM,NOC,MSH,ICPC2P,CHV,NDFRT,SNM,RCD,NCI,SNOMEDCT_US,NCI_FDA,NCI_NICHD,MEDLINEPLUS,MDR,MEDCIN,ICPC2ICD10ENG,NANDA-I","inst":"C0019080","language":"","string_orig":"bleeding","tui_full":"http://linkedlifedata.com/resource/semanticnetwork/id/T046","inst_full":"http://linkedlifedata.com/resource/umls/id/C0019080"}},{"startNode":{"id":3877,"offset":0},"endNode":{"id":3986,"offset":15},"id":3949,"type":"Mention","features":{"STY":"Finding","Experiencer":"Patient","Negation":"Affirmed","PREF":"Complaint","TUI":"T033","Temporality":"Recent","tui_full":"http://linkedlifedata.com/resource/semanticnetwork/id/T033","VOCABS":"CPT,LNC,CHV,SNOMEDCT_US,NCI,MEDCIN,SNMI","inst":"C0277786","language":"","string_orig":"chief complaint","inst_full":"http://linkedlifedata.com/resource/umls/id/C0277786"}},{"startNode":{"id":3631,"offset":1108},"endNode":{"id":3632,"offset":1112},"id":3950,"type":"Mention","features":{"TUI":"T121","Experiencer":"Patient","Negation":"Affirmed","PREF":"Stop","STY":"Pharmacologic Substance","Temporality":"Recent","VOCABS":"MMSL","inst":"C0723457","language":"","tui_full":"http://linkedlifedata.com/resource/semanticnetwork/id/T121","string_orig":"stop","inst_full":"http://linkedlifedata.com/resource/umls/id/C0723457"}},{"startNode":{"id":3987,"offset":20},"endNode":{"id":3988,"offset":26},"id":3951,"type":"Mention","features":{"inst":"C4554530","Experiencer":"Patient","Negation":"Affirmed","PREF":"Bloody","STY":"Finding","TUI":"T033","Temporality":"Recent","VOCABS":"LNC,MTH","language":"","tui_full":"http://linkedlifedata.com/resource/semanticnetwork/id/T033","string_orig":"bloody","inst_full":"http://linkedlifedata.com/resource/umls/id/C4554530"}},{"startNode":{"id":3633,"offset":1157},"endNode":{"id":3634,"offset":1160},"id":3952,"type":"Mention","features":{"language":"","Experiencer":"Patient","Negation":"Affirmed","PREF":"Ending","STY":"Temporal Concept","TUI":"T079","Temporality":"Recent","tui_full":"http://linkedlifedata.com/resource/semanticnetwork/id/T079","VOCABS":"LNC,NCI","inst":"C2746065","string_orig":"end","inst_full":"http://linkedlifedata.com/resource/umls/id/C2746065"}},{"startNode":{"id":3989,"offset":35},"endNode":{"id":3990,"offset":40},"id":3953,"type":"Mention","features":{"Experiencer":"Patient","Negation":"Affirmed","PREF":"Penile","STY":"Body Part, Organ, or Organ Component","TUI":"T023","Temporality":"Recent","VOCABS":"CSP,MTH,LNC,MSH,NCI_NCI-GLOSS,CHV,LCH,RCD,SNOMEDCT_US,SNM,AOD,LCH_NW,PSY,FMA,HL7V2.5,NCI,UWDA","tui_full":"http://linkedlifedata.com/resource/semanticnetwork/id/T023","inst":"C0030851","language":"","string_orig":"penis","inst_full":"http://linkedlifedata.com/resource/umls/id/C0030851"}},{"startNode":{"id":3635,"offset":1168},"endNode":{"id":3636,"offset":1173},"id":3954,"type":"Mention","features":{"Negation":"Affirmed","Experiencer":"Patient","PREF":"Penile","STY":"Body Part, Organ, or Organ Component","TUI":"T023","Temporality":"Recent","VOCABS":"CSP,MTH,LNC,MSH,NCI_NCI-GLOSS,CHV,LCH,RCD,SNOMEDCT_US,SNM,AOD,LCH_NW,PSY,FMA,HL7V2.5,NCI,UWDA","inst":"C0030851","tui_full":"http://linkedlifedata.com/resource/semanticnetwork/id/T023","language":"","string_orig":"penis","inst_full":"http://linkedlifedata.com/resource/umls/id/C0030851"}},{"startNode":{"id":3800,"offset":3284},"endNode":{"id":3801,"offset":3288},"id":3955,"type":"Mention","features":{"TUI":"T037","Experiencer":"Patient","Negation":"Affirmed","PREF":"Lacerated","STY":"Injury or Poisoning","Temporality":"Recent","VOCABS":"CHV,SNM,RCD,SNOMEDCT_US,ICPC2ICD10ENG","inst":"C0043246","tui_full":"http://linkedlifedata.com/resource/semanticnetwork/id/T037","language":"","string_orig":"tear","inst_full":"http://linkedlifedata.com/resource/umls/id/C0043246"}},{"startNode":{"id":3637,"offset":1221},"endNode":{"id":3638,"offset":1225},"id":3956,"type":"Mention","features":{"Negation":"Affirmed","Experiencer":"Patient","tui_full":"http://linkedlifedata.com/resource/semanticnetwork/id/T033","PREF":"Does","STY":"Finding","TUI":"T033","Temporality":"Recent","VOCABS":"SNOMEDCT_US","inst":"C1272751","language":"","string_orig":"does","inst_full":"http://linkedlifedata.com/resource/umls/id/C1272751"}},{"startNode":{"id":3991,"offset":43},"endNode":{"id":3992,"offset":69},"id":3957,"type":"Mention","features":{"TUI":"T033","PREF":"History","Experiencer":"Patient","Negation":"Affirmed","STY":"Finding","Temporality":"Recent","VOCABS":"LNC,MTH,SNOMEDCT_US,MEDCIN,COSTAR,CPT","inst":"C0262512","language":"","string_orig":"history of present illness","inst_full":"http://linkedlifedata.com/resource/umls/id/C0262512","tui_full":"http://linkedlifedata.com/resource/semanticnetwork/id/T033"}},{"startNode":{"id":3639,"offset":1267},"endNode":{"id":3640,"offset":1275},"id":3958,"type":"Mention","features":{"TUI":"T061","Experiencer":"Patient","Negation":"Negated","PREF":"Drainage","STY":"Therapeutic or Preventive Procedure","Temporality":"Recent","VOCABS":"MSH,LCH,LNC,RCD,NCI,SNOMEDCT_US","inst":"C0013103","language":"","string_orig":"drainage","tui_full":"http://linkedlifedata.com/resource/semanticnetwork/id/T061","inst_full":"http://linkedlifedata.com/resource/umls/id/C0013103"}},{"startNode":{"id":3641,"offset":1279},"endNode":{"id":3642,"offset":1288},"id":3959,"type":"Mention","features":{"PREF":"Release","Experiencer":"Patient","Negation":"Negated","STY":"Health Care Activity","TUI":"T058","Temporality":"Recent","VOCABS":"CHV","inst":"C0030685","language":"","tui_full":"http://linkedlifedata.com/resource/semanticnetwork/id/T058","string_orig":"discharge","inst_full":"http://linkedlifedata.com/resource/umls/id/C0030685"}},{"startNode":{"id":3802,"offset":3296},"endNode":{"id":3803,"offset":3300},"id":3792,"type":"Mention","features":{"Experiencer":"Patient","Negation":"Affirmed","PREF":"Skin NOS","STY":"Body System","tui_full":"http://linkedlifedata.com/resource/semanticnetwork/id/T022","TUI":"T022","Temporality":"Recent","VOCABS":"CSP,CHV,AOD","inst":"C1123023","language":"","string_orig":"skin","inst_full":"http://linkedlifedata.com/resource/umls/id/C1123023"}},{"startNode":{"id":3580,"offset":3311},"endNode":{"id":3581,"offset":3315},"id":3793,"type":"Mention","features":{"PREF":"mass","Experiencer":"Patient","Negation":"Affirmed","STY":"Finding","TUI":"T033","Temporality":"Recent","VOCABS":"MEDCIN","inst":"C2136992","tui_full":"http://linkedlifedata.com/resource/semanticnetwork/id/T033","language":"","string_orig":"mass","inst_full":"http://linkedlifedata.com/resource/umls/id/C2136992"}},{"startNode":{"id":3643,"offset":1298},"endNode":{"id":3644,"offset":1303},"id":3794,"type":"Mention","features":{"VOCABS":"CSP,MTH,LNC,MSH,NCI_NCI-GLOSS,CHV,LCH,RCD,SNOMEDCT_US,SNM,AOD,LCH_NW,PSY,FMA,HL7V2.5,NCI,UWDA","Experiencer":"Patient","Negation":"Negated","PREF":"Penile","STY":"Body Part, Organ, or Organ Component","TUI":"T023","Temporality":"Recent","inst":"C0030851","language":"","string_orig":"penis","tui_full":"http://linkedlifedata.com/resource/semanticnetwork/id/T023","inst_full":"http://linkedlifedata.com/resource/umls/id/C0030851"}},{"startNode":{"id":3804,"offset":3332},"endNode":{"id":3805,"offset":3337},"id":3795,"type":"Mention","features":{"PREF":"Glans","Experiencer":"Patient","Negation":"Affirmed","STY":"Body Part, Organ, or Organ Component","TUI":"T023","tui_full":"http://linkedlifedata.com/resource/semanticnetwork/id/T023","Temporality":"Recent","VOCABS":"HL7V2.5","inst":"C1550261","language":"","string_orig":"glans","inst_full":"http://linkedlifedata.com/resource/umls/id/C1550261"}},{"startNode":{"id":3645,"offset":1316},"endNode":{"id":3646,"offset":1322},"id":3796,"type":"Mention","features":{"PREF":"Fevers","Experiencer":"Patient","Negation":"Negated","STY":"Sign or Symptom","TUI":"T184","Temporality":"Recent","VOCABS":"CHV,MSH","inst":"C0015967","language":"","string_orig":"fevers","inst_full":"http://linkedlifedata.com/resource/umls/id/C0015967","tui_full":"http://linkedlifedata.com/resource/semanticnetwork/id/T184"}},{"startNode":{"id":3806,"offset":3338},"endNode":{"id":3807,"offset":3342},"id":3797,"type":"Mention","features":{"TUI":"T033","Experiencer":"Patient","Negation":"Affirmed","PREF":"Near","STY":"Finding","Temporality":"Recent","VOCABS":"RCD,SNOMEDCT_US","inst":"C0475806","language":"","string_orig":"near","tui_full":"http://linkedlifedata.com/resource/semanticnetwork/id/T033","inst_full":"http://linkedlifedata.com/resource/umls/id/C0475806"}},{"startNode":{"id":3647,"offset":1326},"endNode":{"id":3648,"offset":1332},"id":3798,"type":"Mention","features":{"VOCABS":"LNC,MSH,NOC,MTH,HPO,ICPC2P,NCI_CTCAE,ICPC,CHV,SNM,NDFRT,SNOMEDCT_US,NCI,SNMI,NCI_FDA,NCI_NICHD,ICPC2ICD10ENG,MDR,MEDCIN,ICPC2EENG","Experiencer":"Patient","tui_full":"http://linkedlifedata.com/resource/semanticnetwork/id/T184","Negation":"Negated","PREF":"Chills","STY":"Sign or Symptom","TUI":"T184","Temporality":"Recent","inst":"C0085593","language":"","string_orig":"chills","inst_full":"http://linkedlifedata.com/resource/umls/id/C0085593"}},{"startNode":{"id":3808,"offset":3347},"endNode":{"id":3809,"offset":3362},"id":3799,"type":"Mention","features":{"Temporality":"Recent","Experiencer":"Patient","Negation":"Affirmed","PREF":"Urethral meatus","STY":"Body Space or Junction","TUI":"T030","VOCABS":"UWDA,CHV,SNM,FMA,SNOMEDCT_US,SNMI","inst":"C0227744","language":"","string_orig":"urethral meatus","tui_full":"http://linkedlifedata.com/resource/semanticnetwork/id/T030","inst_full":"http://linkedlifedata.com/resource/umls/id/C0227744"}},{"startNode":{"id":3566,"offset":1333},"endNode":{"id":3567,"offset":1341},"id":3800,"type":"Mention","features":{"Negation":"Negated","Experiencer":"Patient","PREF":"Recent","tui_full":"http://linkedlifedata.com/resource/semanticnetwork/id/T079","STY":"Temporal Concept","TUI":"T079","Temporality":"Recent","VOCABS":"SNOMEDCT_US,SNMI","inst":"C0332185","language":"","string_orig":"recently","inst_full":"http://linkedlifedata.com/resource/umls/id/C0332185"}},{"startNode":{"id":3649,"offset":1359},"endNode":{"id":3650,"offset":1377},"id":3801,"type":"Mention","features":{"Experiencer":"Patient","Negation":"Negated","PREF":"Nausea or vomiting","STY":"Finding","TUI":"T033","Temporality":"Recent","VOCABS":"LNC","inst":"C3843946","language":"","tui_full":"http://linkedlifedata.com/resource/semanticnetwork/id/T033","string_orig":"nausea or vomiting","inst_full":"http://linkedlifedata.com/resource/umls/id/C3843946"}},{"startNode":{"id":3875,"offset":86},"endNode":{"id":3876,"offset":90},"id":3802,"type":"Mention","features":{"Temporality":"Recent","Experiencer":"Patient","Negation":"Affirmed","PREF":"Year","STY":"Temporal Concept","TUI":"T079","VOCABS":"CHV,NCI_UCUM,RCD,SNOMEDCT_US,HL7V3.0,MTH","inst":"C0439234","language":"","string_orig":"year","tui_full":"http://linkedlifedata.com/resource/semanticnetwork/id/T079","inst_full":"http://linkedlifedata.com/resource/umls/id/C0439234"}},{"startNode":{"id":3582,"offset":3365},"endNode":{"id":3583,"offset":3373},"id":3803,"type":"Mention","features":{"TUI":"T046","Experiencer":"Patient","Negation":"Affirmed","PREF":"Bleeding","STY":"Pathologic Function","Temporality":"Recent","VOCABS":"CSP,LNC,OMIM,NOC,MSH,ICPC2P,CHV,NDFRT,SNM,RCD,NCI,SNOMEDCT_US,NCI_FDA,NCI_NICHD,MEDLINEPLUS,MDR,MEDCIN,ICPC2ICD10ENG,NANDA-I","inst":"C0019080","language":"","string_orig":"bleeding","tui_full":"http://linkedlifedata.com/resource/semanticnetwork/id/T046","inst_full":"http://linkedlifedata.com/resource/umls/id/C0019080"}},{"startNode":{"id":3651,"offset":1408},"endNode":{"id":3652,"offset":1417},"id":3804,"type":"Mention","features":{"Experiencer":"Patient","Negation":"Negated","PREF":"Release","STY":"Health Care Activity","TUI":"T058","tui_full":"http://linkedlifedata.com/resource/semanticnetwork/id/T058","Temporality":"Recent","VOCABS":"CHV","inst":"C0030685","language":"","string_orig":"discharge","inst_full":"http://linkedlifedata.com/resource/umls/id/C0030685"}},{"startNode":{"id":3554,"offset":91},"endNode":{"id":3555,"offset":94},"id":3805,"type":"Mention","features":{"Negation":"Affirmed","Experiencer":"Patient","PREF":"Old","STY":"Temporal Concept","tui_full":"http://linkedlifedata.com/resource/semanticnetwork/id/T079","TUI":"T079","Temporality":"Recent","VOCABS":"MTH,CHV,NCI,SNOMEDCT_US,SNMI","inst":"C0580836","language":"","string_orig":"old","inst_full":"http://linkedlifedata.com/resource/umls/id/C0580836"}},{"startNode":{"id":3884,"offset":137},"endNode":{"id":3885,"offset":157},"id":3806,"type":"Mention","features":{"Negation":"Affirmed","Experiencer":"Patient","PREF":"Emergency","STY":"Health Care Related Organization","TUI":"T093","Temporality":"Recent","VOCABS":"CHV","inst":"C0562508","tui_full":"http://linkedlifedata.com/resource/semanticnetwork/id/T093","language":"","string_orig":"emergency department","inst_full":"http://linkedlifedata.com/resource/umls/id/C0562508"}},{"startNode":{"id":3653,"offset":1427},"endNode":{"id":3654,"offset":1432},"id":3807,"type":"Mention","features":{"inst":"C0030851","Experiencer":"Patient","Negation":"Negated","PREF":"Penile","STY":"Body Part, Organ, or Organ Component","TUI":"T023","Temporality":"Recent","VOCABS":"CSP,MTH,LNC,MSH,NCI_NCI-GLOSS,CHV,LCH,RCD,SNOMEDCT_US,SNM,AOD,LCH_NW,PSY,FMA,HL7V2.5,NCI,UWDA","language":"","string_orig":"penis","tui_full":"http://linkedlifedata.com/resource/semanticnetwork/id/T023","inst_full":"http://linkedlifedata.com/resource/umls/id/C0030851"}},{"startNode":{"id":3810,"offset":3377},"endNode":{"id":3811,"offset":3386},"id":3808,"type":"Mention","features":{"Experiencer":"Patient","Negation":"Affirmed","PREF":"Current","STY":"Temporal Concept","TUI":"T079","Temporality":"Recent","VOCABS":"CHV,SNOMEDCT_US,SNMI","inst":"C0521116","language":"","string_orig":"currently","tui_full":"http://linkedlifedata.com/resource/semanticnetwork/id/T079","inst_full":"http://linkedlifedata.com/resource/umls/id/C0521116"}},{"startNode":{"id":3655,"offset":1460},"endNode":{"id":3656,"offset":1472},"id":3809,"type":"Mention","features":{"string_orig":"skin lesions","Experiencer":"Patient","Negation":"Negated","PREF":"Skin lesion","STY":"Disease or Syndrome","TUI":"T047","Temporality":"Recent","tui_full":"http://linkedlifedata.com/resource/semanticnetwork/id/T047","VOCABS":"NOC,OMIM,MEDCIN","inst":"C0037284","language":"","inst_full":"http://linkedlifedata.com/resource/umls/id/C0037284"}},{"startNode":{"id":3894,"offset":169},"endNode":{"id":3895,"offset":178},"id":3810,"type":"Mention","features":{"Experiencer":"Patient","Negation":"Affirmed","PREF":"Complaint","STY":"Finding","TUI":"T033","Temporality":"Recent","VOCABS":"LNC,SNM,SNOMEDCT_US,CHV","tui_full":"http://linkedlifedata.com/resource/semanticnetwork/id/T033","inst":"C0277786","language":"","string_orig":"complaint","inst_full":"http://linkedlifedata.com/resource/umls/id/C0277786"}},{"startNode":{"id":3812,"offset":3411},"endNode":{"id":3813,"offset":3415},"id":3811,"type":"Mention","features":{"Experiencer":"Patient","Negation":"Negated","PREF":"Sign, NOS","STY":"Finding","TUI":"T033","Temporality":"Recent","VOCABS":"NCI,SNOMEDCT_US","inst":"C0311392","language":"","string_orig":"sign","inst_full":"http://linkedlifedata.com/resource/umls/id/C0311392","tui_full":"http://linkedlifedata.com/resource/semanticnetwork/id/T033"}},{"startNode":{"id":3556,"offset":184},"endNode":{"id":3557,"offset":192},"id":3812,"type":"Mention","features":{"Negation":"Affirmed","Experiencer":"Patient","PREF":"Bleeding","STY":"Pathologic Function","TUI":"T046","Temporality":"Recent","VOCABS":"CSP,LNC,OMIM,NOC,MSH,ICPC2P,CHV,NDFRT,SNM,RCD,NCI,SNOMEDCT_US,NCI_FDA,NCI_NICHD,MEDLINEPLUS,MDR,MEDCIN,ICPC2ICD10ENG,NANDA-I","inst":"C0019080","language":"","string_orig":"bleeding","tui_full":"http://linkedlifedata.com/resource/semanticnetwork/id/T046","inst_full":"http://linkedlifedata.com/resource/umls/id/C0019080"}},{"startNode":{"id":3657,"offset":1480},"endNode":{"id":3658,"offset":1485},"id":3813,"type":"Mention","features":{"TUI":"T023","Experiencer":"Patient","Negation":"Negated","PREF":"Penile","STY":"Body Part, Organ, or Organ Component","Temporality":"Recent","VOCABS":"CSP,MTH,LNC,MSH,NCI_NCI-GLOSS,CHV,LCH,RCD,SNOMEDCT_US,SNM,AOD,LCH_NW,PSY,FMA,HL7V2.5,NCI,UWDA","inst":"C0030851","language":"","tui_full":"http://linkedlifedata.com/resource/semanticnetwork/id/T023","string_orig":"penis","inst_full":"http://linkedlifedata.com/resource/umls/id/C0030851"}},{"startNode":{"id":3584,"offset":3419},"endNode":{"id":3814,"offset":3438},"id":3814,"type":"Mention","features":{"Experiencer":"Patient","Negation":"Negated","PREF":"Secondary Infection","STY":"Disease or Syndrome","TUI":"T047","Temporality":"Recent","VOCABS":"CSP,CHV,MSH,RCD,MDR,SNOMEDCT_US,AOD","inst":"C0442886","language":"","string_orig":"secondary infection","tui_full":"http://linkedlifedata.com/resource/semanticnetwork/id/T047","inst_full":"http://linkedlifedata.com/resource/umls/id/C0442886"}},{"startNode":{"id":3568,"offset":1495},"endNode":{"id":3569,"offset":1498},"id":3815,"type":"Mention","features":{"Experiencer":"Patient","Negation":"Negated","PREF":"new","STY":"Finding","TUI":"T033","Temporality":"Recent","VOCABS":"HL7V3.0","tui_full":"http://linkedlifedata.com/resource/semanticnetwork/id/T033","inst":"C1578513","language":"","string_orig":"new","inst_full":"http://linkedlifedata.com/resource/umls/id/C1578513"}},{"startNode":{"id":3659,"offset":1559},"endNode":{"id":3660,"offset":1563},"id":3816,"type":"Mention","features":{"Negation":"Affirmed","Experiencer":"Patient","PREF":"Head, NOS","STY":"Body Location or Region","TUI":"T029","Temporality":"Recent","VOCABS":"CSP,MTH,MSH,OMIM,CST,LNC,LCH,SNM,RCD,SNOMEDCT_US,NCI,HL7V2.5,LCH_NW,AOD,FMA,CHV,UWDA","inst":"C0018670","language":"","string_orig":"head","tui_full":"http://linkedlifedata.com/resource/semanticnetwork/id/T029","inst_full":"http://linkedlifedata.com/resource/umls/id/C0018670"}},{"startNode":{"id":3910,"offset":205},"endNode":{"id":3911,"offset":210},"id":3817,"type":"Mention","features":{"PREF":"Penile","Experiencer":"Patient","Negation":"Affirmed","STY":"Body Part, Organ, or Organ Component","tui_full":"http://linkedlifedata.com/resource/semanticnetwork/id/T023","TUI":"T023","Temporality":"Recent","VOCABS":"CSP,MTH,LNC,MSH,NCI_NCI-GLOSS,CHV,LCH,RCD,SNOMEDCT_US,SNM,AOD,LCH_NW,PSY,FMA,HL7V2.5,NCI,UWDA","inst":"C0030851","language":"","string_orig":"penis","inst_full":"http://linkedlifedata.com/resource/umls/id/C0030851"}},{"startNode":{"id":3815,"offset":3447},"endNode":{"id":3816,"offset":3451},"id":3818,"type":"Mention","features":{"TUI":"T079","PREF":"Time","Experiencer":"Patient","Negation":"Negated","STY":"Temporal Concept","Temporality":"Recent","VOCABS":"CHV","tui_full":"http://linkedlifedata.com/resource/semanticnetwork/id/T079","inst":"C0040223","language":"","string_orig":"time","inst_full":"http://linkedlifedata.com/resource/umls/id/C0040223"}},{"startNode":{"id":3661,"offset":1571},"endNode":{"id":3662,"offset":1576},"id":3819,"type":"Mention","features":{"PREF":"Penile","Experiencer":"Patient","Negation":"Affirmed","STY":"Body Part, Organ, or Organ Component","TUI":"T023","Temporality":"Recent","VOCABS":"CSP,MTH,LNC,MSH,NCI_NCI-GLOSS,CHV,LCH,RCD,SNOMEDCT_US,SNM,AOD,LCH_NW,PSY,FMA,HL7V2.5,NCI,UWDA","inst":"C0030851","tui_full":"http://linkedlifedata.com/resource/semanticnetwork/id/T023","language":"","string_orig":"penis","inst_full":"http://linkedlifedata.com/resource/umls/id/C0030851"}},{"startNode":{"id":3817,"offset":3464},"endNode":{"id":3818,"offset":3473},"id":3820,"type":"Mention","features":{"PREF":"Orchis","Experiencer":"Patient","Negation":"Affirmed","STY":"Body Part, Organ, or Organ Component","TUI":"T023","Temporality":"Recent","VOCABS":"CHV,MSH,NCI,AOD","inst":"C0039597","language":"","string_orig":"testicles","tui_full":"http://linkedlifedata.com/resource/semanticnetwork/id/T023","inst_full":"http://linkedlifedata.com/resource/umls/id/C0039597"}},{"startNode":{"id":3920,"offset":268},"endNode":{"id":3921,"offset":271},"id":3821,"type":"Mention","features":{"STY":"Temporal Concept","Experiencer":"Patient","Negation":"Affirmed","PREF":"Ending","TUI":"T079","Temporality":"Recent","tui_full":"http://linkedlifedata.com/resource/semanticnetwork/id/T079","VOCABS":"LNC,NCI","inst":"C2746065","language":"","string_orig":"end","inst_full":"http://linkedlifedata.com/resource/umls/id/C2746065"}},{"startNode":{"id":3663,"offset":1601},"endNode":{"id":3664,"offset":1606},"id":3822,"type":"Mention","features":{"STY":"Body Part, Organ, or Organ Component","Experiencer":"Patient","Negation":"Affirmed","PREF":"Penile","TUI":"T023","tui_full":"http://linkedlifedata.com/resource/semanticnetwork/id/T023","Temporality":"Recent","VOCABS":"CSP,MTH,LNC,MSH,NCI_NCI-GLOSS,CHV,LCH,RCD,SNOMEDCT_US,SNM,AOD,LCH_NW,PSY,FMA,HL7V2.5,NCI,UWDA","inst":"C0030851","language":"","string_orig":"penis","inst_full":"http://linkedlifedata.com/resource/umls/id/C0030851"}},{"startNode":{"id":3819,"offset":3492},"endNode":{"id":3820,"offset":3498},"id":3823,"type":"Mention","features":{"VOCABS":"NCI","Experiencer":"Patient","Negation":"Affirmed","PREF":"Normal","STY":"Finding","TUI":"T033","Temporality":"Recent","inst":"C0231683","language":"","string_orig":"normal","inst_full":"http://linkedlifedata.com/resource/umls/id/C0231683","tui_full":"http://linkedlifedata.com/resource/semanticnetwork/id/T033"}},{"startNode":{"id":3665,"offset":1616},"endNode":{"id":3666,"offset":1621},"id":3824,"type":"Mention","features":{"Negation":"Affirmed","Experiencer":"Patient","PREF":"Year","STY":"Temporal Concept","TUI":"T079","Temporality":"Recent","VOCABS":"CHV,RCD,SNOMEDCT_US","inst":"C0439234","language":"","string_orig":"years","tui_full":"http://linkedlifedata.com/resource/semanticnetwork/id/T079","inst_full":"http://linkedlifedata.com/resource/umls/id/C0439234"}},{"startNode":{"id":3667,"offset":1680},"endNode":{"id":3668,"offset":1686},"id":3825,"type":"Mention","features":{"Experiencer":"Patient","Negation":"Negated","tui_full":"http://linkedlifedata.com/resource/semanticnetwork/id/T184","PREF":"Fevers","STY":"Sign or Symptom","TUI":"T184","Temporality":"Recent","VOCABS":"CHV,MSH","inst":"C0015967","language":"","string_orig":"fevers","inst_full":"http://linkedlifedata.com/resource/umls/id/C0015967"}},{"startNode":{"id":3821,"offset":3507},"endNode":{"id":3822,"offset":3511},"id":3826,"type":"Mention","features":{"PREF":"Painful","Experiencer":"Patient","Negation":"Negated","STY":"Sign or Symptom","TUI":"T184","Temporality":"Recent","VOCABS":"CSP,CHV,AOD,BI,ICPC2ICD10ENG,ICPC2P,MEDCIN,PDQ","tui_full":"http://linkedlifedata.com/resource/semanticnetwork/id/T184","inst":"C0030193","language":"","string_orig":"pain","inst_full":"http://linkedlifedata.com/resource/umls/id/C0030193"}},{"startNode":{"id":3669,"offset":1688},"endNode":{"id":3670,"offset":1694},"id":3827,"type":"Mention","features":{"Negation":"Negated","Experiencer":"Patient","PREF":"Chills","STY":"Sign or Symptom","TUI":"T184","Temporality":"Recent","VOCABS":"LNC,MSH,NOC,MTH,HPO,ICPC2P,NCI_CTCAE,ICPC,CHV,SNM,NDFRT,SNOMEDCT_US,NCI,SNMI,NCI_FDA,NCI_NICHD,ICPC2ICD10ENG,MDR,MEDCIN,ICPC2EENG","tui_full":"http://linkedlifedata.com/resource/semanticnetwork/id/T184","inst":"C0085593","language":"","string_orig":"chills","inst_full":"http://linkedlifedata.com/resource/umls/id/C0085593"}},{"startNode":{"id":3671,"offset":1699},"endNode":{"id":3672,"offset":1711},"id":3828,"type":"Mention","features":{"Temporality":"Recent","Experiencer":"Patient","Negation":"Negated","PREF":"Night sweat","STY":"Sign or Symptom","TUI":"T184","tui_full":"http://linkedlifedata.com/resource/semanticnetwork/id/T184","VOCABS":"MTH,LNC,NOC,HPO,BI,ICPC2P,CHV,SNM,ICD10CM,RCD,SNOMEDCT_US,SNMI,NCI_NICHD,NCI,MDR,DXP,PDQ,COSTAR,MEDCIN","inst":"C0028081","language":"","string_orig":"night sweats","inst_full":"http://linkedlifedata.com/resource/umls/id/C0028081"}},{"startNode":{"id":3673,"offset":1724},"endNode":{"id":3674,"offset":1749},"id":3829,"type":"Mention","features":{"PREF":"Unintentional weight gain","Experiencer":"Patient","Negation":"Negated","STY":"Finding","TUI":"T033","Temporality":"Recent","tui_full":"http://linkedlifedata.com/resource/semanticnetwork/id/T033","VOCABS":"SNOMEDCT_US","inst":"C3714343","language":"","string_orig":"unintentional weight gain","inst_full":"http://linkedlifedata.com/resource/umls/id/C3714343"}},{"startNode":{"id":3675,"offset":1787},"endNode":{"id":3676,"offset":1793},"id":3830,"type":"Mention","features":{"PREF":"Rashes","Experiencer":"Patient","Negation":"Negated","tui_full":"http://linkedlifedata.com/resource/semanticnetwork/id/T184","STY":"Sign or Symptom","TUI":"T184","Temporality":"Recent","VOCABS":"LNC,SNM,MEDLINEPLUS,CHV","inst":"C0015230","language":"","string_orig":"rashes","inst_full":"http://linkedlifedata.com/resource/umls/id/C0015230"}},{"startNode":{"id":3936,"offset":279},"endNode":{"id":3937,"offset":284},"id":3831,"type":"Mention","features":{"Negation":"Affirmed","Experiencer":"Patient","PREF":"Penile","STY":"Body Part, Organ, or Organ Component","TUI":"T023","Temporality":"Recent","VOCABS":"CSP,MTH,LNC,MSH,NCI_NCI-GLOSS,CHV,LCH,RCD,SNOMEDCT_US,SNM,AOD,LCH_NW,PSY,FMA,HL7V2.5,NCI,UWDA","inst":"C0030851","language":"","string_orig":"penis","inst_full":"http://linkedlifedata.com/resource/umls/id/C0030851","tui_full":"http://linkedlifedata.com/resource/semanticnetwork/id/T023"}},{"startNode":{"id":3677,"offset":1798},"endNode":{"id":3678,"offset":1805},"id":3832,"type":"Mention","features":{"language":"","Experiencer":"Patient","Negation":"Negated","PREF":"Lesion","STY":"Finding","TUI":"T033","Temporality":"Recent","tui_full":"http://linkedlifedata.com/resource/semanticnetwork/id/T033","VOCABS":"CHV,PSY","inst":"C0221198","string_orig":"lesions","inst_full":"http://linkedlifedata.com/resource/umls/id/C0221198"}},{"startNode":{"id":3586,"offset":3515},"endNode":{"id":3587,"offset":3519},"id":3833,"type":"Mention","features":{"TUI":"T033","Experiencer":"Patient","Negation":"Negated","PREF":"mass","STY":"Finding","tui_full":"http://linkedlifedata.com/resource/semanticnetwork/id/T033","Temporality":"Recent","VOCABS":"MEDCIN","inst":"C2136992","language":"","string_orig":"mass","inst_full":"http://linkedlifedata.com/resource/umls/id/C2136992"}},{"startNode":{"id":3943,"offset":305},"endNode":{"id":3944,"offset":309},"id":3834,"type":"Mention","features":{"Experiencer":"Patient","Negation":"Affirmed","PREF":"Year","STY":"Temporal Concept","TUI":"T079","Temporality":"Recent","VOCABS":"CHV,NCI_UCUM,RCD,SNOMEDCT_US,HL7V3.0,MTH","inst":"C0439234","language":"","tui_full":"http://linkedlifedata.com/resource/semanticnetwork/id/T079","string_orig":"year","inst_full":"http://linkedlifedata.com/resource/umls/id/C0439234"}},{"startNode":{"id":3679,"offset":1821},"endNode":{"id":3680,"offset":1825},"id":3835,"type":"Mention","features":{"Negation":"Negated","Experiencer":"Patient","PREF":"Skin NOS","STY":"Body System","TUI":"T022","Temporality":"Recent","VOCABS":"CSP,CHV,AOD","inst":"C1123023","tui_full":"http://linkedlifedata.com/resource/semanticnetwork/id/T022","language":"","string_orig":"skin","inst_full":"http://linkedlifedata.com/resource/umls/id/C1123023"}},{"startNode":{"id":3823,"offset":3546},"endNode":{"id":3824,"offset":3554},"id":3836,"type":"Mention","features":{"inst":"C0018246","Experiencer":"Patient","Negation":"Negated","PREF":"Groins","STY":"Body Location or Region","TUI":"T029","Temporality":"Recent","VOCABS":"SNOMEDCT_VET,CHV,RCD,NCI,SNOMEDCT_US,HL7V2.5,SNMI","language":"","string_orig":"inguinal","inst_full":"http://linkedlifedata.com/resource/umls/id/C0018246","tui_full":"http://linkedlifedata.com/resource/semanticnetwork/id/T029"}},{"startNode":{"id":3825,"offset":3555},"endNode":{"id":3826,"offset":3565},"id":3837,"type":"Mention","features":{"PREF":"adenopathy","Experiencer":"Patient","Negation":"Negated","STY":"Finding","TUI":"T033","Temporality":"Recent","VOCABS":"CHV","inst":"C4282165","language":"","tui_full":"http://linkedlifedata.com/resource/semanticnetwork/id/T033","string_orig":"adenopathy","inst_full":"http://linkedlifedata.com/resource/umls/id/C4282165"}},{"startNode":{"id":3681,"offset":1833},"endNode":{"id":3682,"offset":1837},"id":3838,"type":"Mention","features":{"PREF":"Body","Experiencer":"Patient","Negation":"Negated","STY":"Anatomical Structure","TUI":"T017","Temporality":"Recent","tui_full":"http://linkedlifedata.com/resource/semanticnetwork/id/T017","VOCABS":"UWDA","inst":"C4082212","language":"","string_orig":"body","inst_full":"http://linkedlifedata.com/resource/umls/id/C4082212"}},{"startNode":{"id":3827,"offset":3567},"endNode":{"id":3828,"offset":3578},"id":3839,"type":"Mention","features":{"Experiencer":"Patient","PREF":"Extremity","Negation":"Affirmed","STY":"Body Part, Organ, or Organ Component","TUI":"T023","Temporality":"Recent","tui_full":"http://linkedlifedata.com/resource/semanticnetwork/id/T023","VOCABS":"LNC,PCDS,MSH,NCI,AOD,CHV","inst":"C0015385","language":"","string_orig":"extremities","inst_full":"http://linkedlifedata.com/resource/umls/id/C0015385"}}],[{"startNode":{"id":3552,"offset":4000},"endNode":{"id":3553,"offset":4004},"id":5216,"type":"Phenotype","features":{"majorType":"StrokeStudy","minorType":"tumour","language":"","Experiencer":"Patient","string":"mass","string_orig":"mass","Temporality":"Recent","Negation":"Affirmed"}},{"startNode":{"id":3554,"offset":91},"endNode":{"id":3555,"offset":94},"id":5195,"type":"Phenotype","features":{"majorType":"StrokeStudy","minorType":"time_old","language":"","Experiencer":"Patient","string":"old","string_orig":"old","Temporality":"Recent","Negation":"Affirmed"}},{"startNode":{"id":3556,"offset":184},"endNode":{"id":3557,"offset":192},"id":5196,"type":"Phenotype","features":{"majorType":"StrokeStudy","minorType":"bleeding","language":"","Experiencer":"Patient","string":"bleeding","string_orig":"bleeding","Temporality":"Recent","Negation":"Affirmed"}},{"startNode":{"id":3558,"offset":463},"endNode":{"id":3559,"offset":469},"id":5197,"type":"Phenotype","features":{"majorType":"StrokeStudy","minorType":"time_recent","language":"","Experiencer":"Patient","string":"active","string_orig":"active","Temporality":"Recent","Negation":"Affirmed"}},{"startNode":{"id":3560,"offset":916},"endNode":{"id":3561,"offset":921},"id":5198,"type":"Phenotype","features":{"majorType":"StrokeStudy","minorType":"bleeding","language":"","Experiencer":"Patient","string":"blood","string_orig":"blood","Temporality":"Recent","Negation":"Affirmed"}},{"startNode":{"id":3562,"offset":1048},"endNode":{"id":3563,"offset":1056},"id":5199,"type":"Phenotype","features":{"majorType":"StrokeStudy","minorType":"bleeding","language":"","Experiencer":"Patient","string":"bleeding","string_orig":"bleeding","Temporality":"Recent","Negation":"Affirmed"}},{"startNode":{"id":3564,"offset":1096},"endNode":{"id":3565,"offset":1104},"id":5200,"type":"Phenotype","features":{"majorType":"StrokeStudy","minorType":"bleeding","language":"","Experiencer":"Patient","string":"bleeding","string_orig":"bleeding","Temporality":"Recent","Negation":"Affirmed"}},{"startNode":{"id":3566,"offset":1333},"endNode":{"id":3567,"offset":1341},"id":5201,"type":"Phenotype","features":{"majorType":"StrokeStudy","minorType":"time_recent","language":"","Experiencer":"Patient","string":"recently","string_orig":"recently","Temporality":"Recent","Negation":"Negated"}},{"startNode":{"id":3568,"offset":1495},"endNode":{"id":3569,"offset":1498},"id":5202,"type":"Phenotype","features":{"majorType":"StrokeStudy","minorType":"time_recent","language":"","Experiencer":"Patient","string":"new","string_orig":"new","Temporality":"Recent","Negation":"Negated"}},{"startNode":{"id":3570,"offset":2129},"endNode":{"id":3571,"offset":2134},"id":5203,"type":"Phenotype","features":{"majorType":"StrokeStudy","minorType":"time_old","language":"","Experiencer":"Patient","string":"known","string_orig":"known","Temporality":"Recent","Negation":"Negated"}},{"startNode":{"id":3572,"offset":2306},"endNode":{"id":3573,"offset":2311},"id":5204,"type":"Phenotype","features":{"majorType":"StrokeStudy","minorType":"time_recent","language":"","Experiencer":"Patient","string":"acute","string_orig":"acute","Temporality":"Recent","Negation":"Negated"}},{"startNode":{"id":3574,"offset":2448},"endNode":{"id":3575,"offset":2453},"id":5205,"type":"Phenotype","features":{"majorType":"StrokeStudy","minorType":"bleeding","language":"","Experiencer":"Patient","string":"blood","string_orig":"blood","Temporality":"Recent","Negation":"Affirmed"}},{"startNode":{"id":3576,"offset":2897},"endNode":{"id":3577,"offset":2901},"id":5206,"type":"Phenotype","features":{"majorType":"StrokeStudy","minorType":"tumour","language":"","Experiencer":"Patient","string":"mass","string_orig":"mass","Temporality":"Recent","Negation":"Affirmed"}},{"startNode":{"id":3578,"offset":2996},"endNode":{"id":3579,"offset":3000},"id":5207,"type":"Phenotype","features":{"majorType":"StrokeStudy","minorType":"tumour","language":"","Experiencer":"Patient","string":"mass","string_orig":"mass","Temporality":"Recent","Negation":"Affirmed"}},{"startNode":{"id":3580,"offset":3311},"endNode":{"id":3581,"offset":3315},"id":5208,"type":"Phenotype","features":{"majorType":"StrokeStudy","minorType":"tumour","language":"","Experiencer":"Patient","string":"mass","string_orig":"mass","Temporality":"Recent","Negation":"Affirmed"}},{"startNode":{"id":3582,"offset":3365},"endNode":{"id":3583,"offset":3373},"id":5209,"type":"Phenotype","features":{"majorType":"StrokeStudy","minorType":"bleeding","language":"","Experiencer":"Patient","string":"bleeding","string_orig":"Bleeding","Temporality":"Recent","Negation":"Affirmed"}},{"startNode":{"id":3584,"offset":3419},"endNode":{"id":3585,"offset":3428},"id":5210,"type":"Phenotype","features":{"majorType":"StrokeStudy","minorType":"metast_tumour","language":"","Experiencer":"Patient","string":"secondary","string_orig":"secondary","Temporality":"Recent","Negation":"Negated"}},{"startNode":{"id":3586,"offset":3515},"endNode":{"id":3587,"offset":3519},"id":5211,"type":"Phenotype","features":{"majorType":"StrokeStudy","minorType":"tumour","language":"","Experiencer":"Patient","string":"mass","string_orig":"mass","Temporality":"Recent","Negation":"Negated"}},{"startNode":{"id":3588,"offset":3633},"endNode":{"id":3589,"offset":3639},"id":5212,"type":"Phenotype","features":{"majorType":"StrokeStudy","minorType":"tumour","language":"","Experiencer":"Patient","string":"lesion","string_orig":"lesion","Temporality":"Recent","Negation":"Negated"}},{"startNode":{"id":3590,"offset":3813},"endNode":{"id":3591,"offset":3817},"id":5213,"type":"Phenotype","features":{"majorType":"StrokeStudy","minorType":"tumour","language":"","Experiencer":"Patient","string":"mass","string_orig":"mass","Temporality":"Recent","Negation":"Affirmed"}},{"startNode":{"id":3592,"offset":3849},"endNode":{"id":3593,"offset":3853},"id":5214,"type":"Phenotype","features":{"majorType":"StrokeStudy","minorType":"tumour","language":"","Experiencer":"Patient","string":"mass","string_orig":"mass","Temporality":"Recent","Negation":"Affirmed"}},{"startNode":{"id":3594,"offset":3906},"endNode":{"id":3595,"offset":3910},"id":5215,"type":"Phenotype","features":{"majorType":"StrokeStudy","minorType":"tumour","language":"","Experiencer":"Patient","string":"mass","string_orig":"mass","Temporality":"Recent","Negation":"Affirmed"}}],[{"startNode":{"id":3952,"offset":2794},"endNode":{"id":3953,"offset":2865},"id":1792,"type":"Sentence","features":{}},{"startNode":{"id":3954,"offset":2867},"endNode":{"id":3955,"offset":2976},"id":1793,"type":"Sentence","features":{"case":"sentence"}},{"startNode":{"id":3956,"offset":2978},"endNode":{"id":3957,"offset":3104},"id":1794,"type":"Sentence","features":{"case":"sentence"}},{"startNode":{"id":3958,"offset":3106},"endNode":{"id":3959,"offset":3223},"id":1795,"type":"Sentence","features":{"case":"sentence"}},{"startNode":{"id":3960,"offset":3225},"endNode":{"id":3961,"offset":3265},"id":1796,"type":"Sentence","features":{"case":"sentence"}},{"startNode":{"id":3962,"offset":3267},"endNode":{"id":3963,"offset":3363},"id":1797,"type":"Sentence","features":{"case":"sentence"}},{"startNode":{"id":3582,"offset":3365},"endNode":{"id":3964,"offset":3452},"id":1798,"type":"Sentence","features":{"case":"sentence"}},{"startNode":{"id":3965,"offset":3454},"endNode":{"id":3966,"offset":3532},"id":1799,"type":"Sentence","features":{"case":"sentence"}},{"startNode":{"id":3967,"offset":3534},"endNode":{"id":3968,"offset":3566},"id":1800,"type":"Sentence","features":{"case":"sentence"}},{"startNode":{"id":3968,"offset":3566},"endNode":{"id":3969,"offset":3590},"id":1801,"type":"Sentence","features":{}},{"startNode":{"id":3969,"offset":3590},"endNode":{"id":3970,"offset":3620},"id":1802,"type":"Sentence","features":{}},{"startNode":{"id":3971,"offset":3622},"endNode":{"id":3972,"offset":3640},"id":1803,"type":"Sentence","features":{"case":"sentence"}},{"startNode":{"id":3972,"offset":3640},"endNode":{"id":3973,"offset":3696},"id":1804,"type":"Sentence","features":{}},{"startNode":{"id":3974,"offset":3698},"endNode":{"id":3975,"offset":3818},"id":1805,"type":"Sentence","features":{"case":"sentence"}},{"startNode":{"id":3975,"offset":3818},"endNode":{"id":3976,"offset":3854},"id":1806,"type":"Sentence","features":{}},{"startNode":{"id":3977,"offset":3856},"endNode":{"id":3978,"offset":3911},"id":1807,"type":"Sentence","features":{"case":"sentence"}},{"startNode":{"id":3979,"offset":3913},"endNode":{"id":3980,"offset":3971},"id":1808,"type":"Sentence","features":{"case":"sentence"}},{"startNode":{"id":3981,"offset":3973},"endNode":{"id":3982,"offset":4026},"id":1809,"type":"Sentence","features":{"case":"sentence"}},{"startNode":{"id":3983,"offset":4028},"endNode":{"id":3984,"offset":4142},"id":1810,"type":"Sentence","features":{"case":"sentence"}},{"startNode":{"id":3984,"offset":4142},"endNode":{"id":3985,"offset":4143},"id":1811,"type":"Sentence","features":{}},{"startNode":{"id":3877,"offset":0},"endNode":{"id":3878,"offset":41},"id":1754,"type":"Sentence","features":{"case":"sentence"}},{"startNode":{"id":3878,"offset":41},"endNode":{"id":3879,"offset":211},"id":1755,"type":"Sentence","features":{}},{"startNode":{"id":3880,"offset":213},"endNode":{"id":3881,"offset":321},"id":1756,"type":"Sentence","features":{"case":"sentence"}},{"startNode":{"id":3882,"offset":323},"endNode":{"id":3883,"offset":363},"id":1757,"type":"Sentence","features":{"case":"sentence"}},{"startNode":{"id":3886,"offset":365},"endNode":{"id":3887,"offset":422},"id":1758,"type":"Sentence","features":{"case":"sentence"}},{"startNode":{"id":3888,"offset":424},"endNode":{"id":3889,"offset":538},"id":1759,"type":"Sentence","features":{"case":"sentence"}},{"startNode":{"id":3890,"offset":540},"endNode":{"id":3891,"offset":647},"id":1760,"type":"Sentence","features":{"case":"sentence"}},{"startNode":{"id":3892,"offset":649},"endNode":{"id":3893,"offset":865},"id":1761,"type":"Sentence","features":{"case":"sentence"}},{"startNode":{"id":3896,"offset":867},"endNode":{"id":3897,"offset":939},"id":1762,"type":"Sentence","features":{"case":"sentence"}},{"startNode":{"id":3898,"offset":941},"endNode":{"id":3899,"offset":1057},"id":1763,"type":"Sentence","features":{"case":"sentence"}},{"startNode":{"id":3900,"offset":1059},"endNode":{"id":3901,"offset":1242},"id":1764,"type":"Sentence","features":{"case":"sentence"}},{"startNode":{"id":3902,"offset":1244},"endNode":{"id":3903,"offset":1304},"id":1765,"type":"Sentence","features":{"case":"sentence"}},{"startNode":{"id":3904,"offset":1306},"endNode":{"id":3905,"offset":1342},"id":1766,"type":"Sentence","features":{"case":"sentence"}},{"startNode":{"id":3906,"offset":1344},"endNode":{"id":3907,"offset":1378},"id":1767,"type":"Sentence","features":{"case":"sentence"}},{"startNode":{"id":3908,"offset":1380},"endNode":{"id":3909,"offset":1433},"id":1768,"type":"Sentence","features":{"case":"sentence"}},{"startNode":{"id":3912,"offset":1435},"endNode":{"id":3913,"offset":1506},"id":1769,"type":"Sentence","features":{"case":"sentence"}},{"startNode":{"id":3914,"offset":1508},"endNode":{"id":3915,"offset":1622},"id":1770,"type":"Sentence","features":{"case":"sentence"}},{"startNode":{"id":3916,"offset":1624},"endNode":{"id":3917,"offset":1668},"id":1771,"type":"Sentence","features":{"case":"sentence"}},{"startNode":{"id":3918,"offset":1670},"endNode":{"id":3919,"offset":1712},"id":1772,"type":"Sentence","features":{"case":"sentence"}},{"startNode":{"id":3922,"offset":1714},"endNode":{"id":3923,"offset":1758},"id":1773,"type":"Sentence","features":{"case":"sentence"}},{"startNode":{"id":3924,"offset":1760},"endNode":{"id":3925,"offset":1838},"id":1774,"type":"Sentence","features":{"case":"sentence"}},{"startNode":{"id":3925,"offset":1838},"endNode":{"id":3926,"offset":1895},"id":1775,"type":"Sentence","features":{}},{"startNode":{"id":3926,"offset":1895},"endNode":{"id":3927,"offset":1983},"id":1776,"type":"Sentence","features":{}},{"startNode":{"id":3927,"offset":1983},"endNode":{"id":3928,"offset":2039},"id":1777,"type":"Sentence","features":{}},{"startNode":{"id":3929,"offset":2041},"endNode":{"id":3930,"offset":2091},"id":1778,"type":"Sentence","features":{"case":"sentence"}},{"startNode":{"id":3930,"offset":2091},"endNode":{"id":3931,"offset":2112},"id":1779,"type":"Sentence","features":{}},{"startNode":{"id":3931,"offset":2112},"endNode":{"id":3932,"offset":2153},"id":1780,"type":"Sentence","features":{}},{"startNode":{"id":3932,"offset":2153},"endNode":{"id":3933,"offset":2260},"id":1781,"type":"Sentence","features":{}},{"startNode":{"id":3934,"offset":2262},"endNode":{"id":3935,"offset":2321},"id":1782,"type":"Sentence","features":{"case":"sentence"}},{"startNode":{"id":3938,"offset":2323},"endNode":{"id":3939,"offset":2347},"id":1783,"type":"Sentence","features":{"case":"sentence"}},{"startNode":{"id":3940,"offset":2349},"endNode":{"id":3941,"offset":2396},"id":1784,"type":"Sentence","features":{"case":"sentence"}},{"startNode":{"id":3941,"offset":2396},"endNode":{"id":3942,"offset":2549},"id":1785,"type":"Sentence","features":{}},{"startNode":{"id":3942,"offset":2549},"endNode":{"id":3945,"offset":2582},"id":1786,"type":"Sentence","features":{}},{"startNode":{"id":3750,"offset":2584},"endNode":{"id":3946,"offset":2597},"id":1787,"type":"Sentence","features":{"case":"title"}},{"startNode":{"id":3947,"offset":2599},"endNode":{"id":3948,"offset":2640},"id":1788,"type":"Sentence","features":{"case":"sentence"}},{"startNode":{"id":3948,"offset":2640},"endNode":{"id":3949,"offset":2683},"id":1789,"type":"Sentence","features":{}},{"startNode":{"id":3950,"offset":2685},"endNode":{"id":3951,"offset":2715},"id":1790,"type":"Sentence","features":{"case":"sentence"}},{"startNode":{"id":3951,"offset":2715},"endNode":{"id":3952,"offset":2794},"id":1791,"type":"Sentence","features":{}}]]}
